[
    {
        "id": 1,
        "name": "刻耳柏洛斯",
        "raceName": "森林",
        "race": 1,
        "quality": 1,
        "attackID": 244,
        "cardFrame": 7,
        "img": "https://cdnzmg.zmfamily.cn/card/res/herov3/kebls_7_1.png",
        "attack": 95,
        "life": 310,
        "skill1": null,
        "skill2": 81,
        "skill3": 10,
        "atkPro": 17,
        "lifePro": 11,
        "upgradeNum": "0_2_4_10_20_40_50_60_80_150",
        "upgradeGold": "0_120_240_600_1200_1800_2000_3000_3600_4800_9000",
        "lvLife": "310_321_332_343_354_365_376_387_398_409",
        "lvAtk": "95_112_129_146_163_180_197_214_231_248"
    },
    {
        "id": 2,
        "name": "克吕墨涅",
        "raceName": "森林",
        "race": 1,
        "quality": 1,
        "attackID": 244,
        "cardFrame": 7,
        "img": "https://cdnzmg.zmfamily.cn/card/res/herov3/klmn_7_2.png",
        "attack": 100,
        "life": 400,
        "skill1": null,
        "skill2": 81,
        "skill3": 10,
        "atkPro": 16,
        "lifePro": 16,
        "upgradeNum": "0_2_4_10_20_40_50_60_80_150",
        "upgradeGold": "0_120_240_600_1200_1800_2000_3000_3600_4800_9000",
        "lvLife": "400_416_432_448_464_480_496_512_528_544",
        "lvAtk": "100_116_132_148_164_180_196_212_228_244"
    },
    {
        "id": 3,
        "name": "优忒毗",
        "raceName": "森林",
        "race": 1,
        "quality": 1,
        "attackID": 244,
        "cardFrame": 5,
        "img": "https://cdnzmg.zmfamily.cn/card/res/herov3/yrz_5_3.png",
        "attack": 90,
        "life": 270,
        "skill1": 89,
        "skill2": 123,
        "skill3": 236,
        "atkPro": 14,
        "lifePro": 22,
        "upgradeNum": "0_2_4_10_20_40_50_60_80_150",
        "upgradeGold": "0_120_240_600_1200_1800_2000_3000_3600_4800_9000",
        "lvLife": "270_292_314_336_358_380_402_424_446_468",
        "lvAtk": "90_104_118_132_146_160_174_188_202_216"
    },
    {
        "id": 4,
        "name": "卡拉培",
        "raceName": "森林",
        "race": 1,
        "quality": 1,
        "attackID": 244,
        "cardFrame": 5,
        "img": "https://cdnzmg.zmfamily.cn/card/res/herov3/klp_5_4.png",
        "attack": 110,
        "life": 260,
        "skill1": null,
        "skill2": 81,
        "skill3": 163,
        "atkPro": 26,
        "lifePro": 20,
        "upgradeNum": "0_2_4_10_20_40_50_60_80_150",
        "upgradeGold": "0_120_240_600_1200_1800_2000_3000_3600_4800_9000",
        "lvLife": "260_280_300_320_340_360_380_400_420_440",
        "lvAtk": "110_136_162_188_214_240_266_292_318_344"
    },
    {
        "id": 5,
        "name": "格莱埃",
        "raceName": "森林",
        "race": 1,
        "quality": 1,
        "attackID": 244,
        "cardFrame": 2,
        "img": "https://cdnzmg.zmfamily.cn/card/res/herov3/gle_2_5.png",
        "attack": 85,
        "life": 280,
        "skill1": 122,
        "skill2": 37,
        "skill3": 232,
        "atkPro": 12,
        "lifePro": 27,
        "upgradeNum": "0_2_4_10_20_40_50_60_80_150",
        "upgradeGold": "0_120_240_600_1200_1800_2000_3000_3600_4800_9000",
        "lvLife": "280_307_334_361_388_415_442_469_496_523",
        "lvAtk": "85_97_109_121_133_145_157_169_181_193"
    },
    {
        "id": 6,
        "name": "依蕾托",
        "raceName": "森林",
        "race": 1,
        "quality": 2,
        "attackID": 244,
        "cardFrame": 5,
        "img": "https://cdnzmg.zmfamily.cn/card/res/herov3/ylt_5_6.png",
        "attack": 115,
        "life": 400,
        "skill1": 101,
        "skill2": 123,
        "skill3": 102,
        "atkPro": 16,
        "lifePro": 30,
        "upgradeNum": "0_2_4_6_10_20_30_40_60_80_120",
        "upgradeGold": "0_330_660_990_1650_3300_4950_6600_9900_13200_19800",
        "lvLife": "400_430_460_490_520_550_580_610_640_670",
        "lvAtk": "115_131_147_163_179_195_211_227_243_259"
    },
    {
        "id": 7,
        "name": "赫斯帕里得斯",
        "raceName": "森林",
        "race": 1,
        "quality": 2,
        "attackID": 244,
        "cardFrame": 7,
        "img": "https://cdnzmg.zmfamily.cn/card/res/herov3/hsplds_7_7.png",
        "attack": 140,
        "life": 510,
        "skill1": 101,
        "skill2": 82,
        "skill3": 102,
        "atkPro": 17,
        "lifePro": 28,
        "upgradeNum": "0_2_4_6_10_20_30_40_60_80_120",
        "upgradeGold": "0_330_660_990_1650_3300_4950_6600_9900_13200_19800",
        "lvLife": "510_538_566_594_622_650_678_706_734_762",
        "lvAtk": "140_157_174_191_208_225_242_259_276_293"
    },
    {
        "id": 8,
        "name": "塔罗斯",
        "raceName": "森林",
        "race": 1,
        "quality": 2,
        "attackID": 244,
        "cardFrame": 7,
        "img": "https://cdnzmg.zmfamily.cn/card/res/herov3/tls_7_8.png",
        "attack": 160,
        "life": 530,
        "skill1": null,
        "skill2": 82,
        "skill3": 232,
        "atkPro": 15,
        "lifePro": 35,
        "upgradeNum": "0_2_4_6_10_20_30_40_60_80_120",
        "upgradeGold": "0_330_660_990_1650_3300_4950_6600_9900_13200_19800",
        "lvLife": "530_565_600_635_670_705_740_775_810_845",
        "lvAtk": "160_175_190_205_220_235_250_265_280_295"
    },
    {
        "id": 9,
        "name": "欧佛洛绪涅",
        "raceName": "森林",
        "race": 1,
        "quality": 2,
        "attackID": 244,
        "cardFrame": 5,
        "img": "https://cdnzmg.zmfamily.cn/card/res/herov3/oflxn_5_9.png",
        "attack": 105,
        "life": 385,
        "skill1": 101,
        "skill2": 81,
        "skill3": 103,
        "atkPro": 24,
        "lifePro": 20,
        "upgradeNum": "0_2_4_6_10_20_30_40_60_80_120",
        "upgradeGold": "0_330_660_990_1650_3300_4950_6600_9900_13200_19800",
        "lvLife": "385_405_425_445_465_485_505_525_545_565",
        "lvAtk": "105_129_153_177_201_225_249_273_297_321"
    },
    {
        "id": 10,
        "name": "琉喀忒亚",
        "raceName": "森林",
        "race": 1,
        "quality": 2,
        "attackID": 244,
        "cardFrame": 7,
        "img": "https://cdnzmg.zmfamily.cn/card/res/herov3/lkry_7_10.png",
        "attack": 125,
        "life": 395,
        "skill1": 82,
        "skill2": 81,
        "skill3": 237,
        "atkPro": 17,
        "lifePro": 28,
        "upgradeNum": "0_2_4_6_10_20_30_40_60_80_120",
        "upgradeGold": "0_330_660_990_1650_3300_4950_6600_9900_13200_19800",
        "lvLife": "395_423_451_479_507_535_563_591_619_647",
        "lvAtk": "125_142_159_176_193_210_227_244_261_278"
    },
    {
        "id": 11,
        "name": "塞墨勒",
        "raceName": "森林",
        "race": 1,
        "quality": 2,
        "attackID": 246,
        "cardFrame": 3,
        "img": "https://cdnzmg.zmfamily.cn/card/res/herov3/sml_3_11.png",
        "attack": 110,
        "life": 450,
        "skill1": 49,
        "skill2": 50,
        "skill3": 106,
        "atkPro": 16,
        "lifePro": 33,
        "upgradeNum": "0_2_4_6_10_20_30_40_60_80_120",
        "upgradeGold": "0_330_660_990_1650_3300_4950_6600_9900_13200_19800",
        "lvLife": "450_483_516_549_582_615_648_681_714_747",
        "lvAtk": "110_126_142_158_174_190_206_222_238_254"
    },
    {
        "id": 12,
        "name": "波利海妮娅",
        "raceName": "森林",
        "race": 1,
        "quality": 2,
        "attackID": 244,
        "cardFrame": 5,
        "img": "https://cdnzmg.zmfamily.cn/card/res/herov3/blhny_5_12.png",
        "attack": 150,
        "life": 580,
        "skill1": null,
        "skill2": 17,
        "skill3": 83,
        "atkPro": 19,
        "lifePro": 20,
        "upgradeNum": "0_2_4_6_10_20_30_40_60_80_120",
        "upgradeGold": "0_330_660_990_1650_3300_4950_6600_9900_13200_19800",
        "lvLife": "580_600_620_640_660_680_700_720_740_760",
        "lvAtk": "150_169_188_207_226_245_264_283_302_321"
    },
    {
        "id": 13,
        "name": "卡吕普索",
        "raceName": "森林",
        "race": 1,
        "quality": 2,
        "attackID": 247,
        "cardFrame": 2,
        "img": "https://cdnzmg.zmfamily.cn/card/res/herov3/klps_2_13.png",
        "attack": 100,
        "life": 390,
        "skill1": 38,
        "skill2": 223,
        "skill3": 39,
        "atkPro": 12,
        "lifePro": 42,
        "upgradeNum": "0_2_4_6_10_20_30_40_60_80_120",
        "upgradeGold": "0_330_660_990_1650_3300_4950_6600_9900_13200_19800",
        "lvLife": "390_432_474_516_558_600_642_684_726_768",
        "lvAtk": "100_112_124_136_148_160_172_184_196_208"
    },
    {
        "id": 14,
        "name": "克利欧",
        "raceName": "森林",
        "race": 1,
        "quality": 3,
        "attackID": 244,
        "cardFrame": 5,
        "img": "https://cdnzmg.zmfamily.cn/card/res/herov3/klo_5_14.png",
        "attack": 125,
        "life": 540,
        "skill1": 102,
        "skill2": 242,
        "skill3": 103,
        "atkPro": 18,
        "lifePro": 39,
        "upgradeNum": "0_2_3_4_6_10_20_30_40_50_80",
        "upgradeGold": "0_840_1260_1680_2520_4200_8400_12600_16800_21000_33600",
        "lvLife": "540_579_618_657_696_735_774_813_852_891",
        "lvAtk": "125_143_161_179_197_215_233_251_269_287"
    },
    {
        "id": 15,
        "name": "赫柏",
        "raceName": "森林",
        "race": 1,
        "quality": 3,
        "attackID": 246,
        "cardFrame": 3,
        "img": "https://cdnzmg.zmfamily.cn/card/res/herov3/hb_3_15.png",
        "attack": 115,
        "life": 490,
        "skill1": 50,
        "skill2": 94,
        "skill3": 55,
        "atkPro": 19,
        "lifePro": 41,
        "upgradeNum": "0_2_3_4_6_10_20_30_40_50_80",
        "upgradeGold": "0_840_1260_1680_2520_4200_8400_12600_16800_21000_33600",
        "lvLife": "490_531_572_613_654_695_736_777_818_859",
        "lvAtk": "115_134_153_172_191_210_229_248_267_286"
    },
    {
        "id": 16,
        "name": "戈耳工",
        "raceName": "森林",
        "race": 1,
        "quality": 3,
        "attackID": 244,
        "cardFrame": 7,
        "img": "https://cdnzmg.zmfamily.cn/card/res/herov3/geg_7_16.png",
        "attack": 185,
        "life": 730,
        "skill1": 17,
        "skill2": 103,
        "skill3": 83,
        "atkPro": 15,
        "lifePro": 52,
        "upgradeNum": "0_2_3_4_6_10_20_30_40_50_80",
        "upgradeGold": "0_840_1260_1680_2520_4200_8400_12600_16800_21000_33600",
        "lvLife": "730_782_834_886_938_990_1042_1094_1146_1198",
        "lvAtk": "185_200_215_230_245_260_275_290_305_320"
    },
    {
        "id": 17,
        "name": "美罗珀",
        "raceName": "森林",
        "race": 1,
        "quality": 3,
        "attackID": 245,
        "cardFrame": 4,
        "img": "https://cdnzmg.zmfamily.cn/card/res/herov3/mlp_4_17.png",
        "attack": 180,
        "life": 680,
        "skill1": 90,
        "skill2": 83,
        "skill3": 31,
        "atkPro": 23,
        "lifePro": 28,
        "upgradeNum": "0_2_3_4_6_10_20_30_40_50_80",
        "upgradeGold": "0_840_1260_1680_2520_4200_8400_12600_16800_21000_33600",
        "lvLife": "680_708_736_764_792_820_848_876_904_932",
        "lvAtk": "180_203_226_249_272_295_318_341_364_387"
    },
    {
        "id": 18,
        "name": "伊莱卡",
        "raceName": "森林",
        "race": 1,
        "quality": 3,
        "attackID": 244,
        "cardFrame": 4,
        "img": "https://cdnzmg.zmfamily.cn/card/res/herov3/ylk_4_18.png",
        "attack": 140,
        "life": 645,
        "skill1": 25,
        "skill2": 210,
        "skill3": 234,
        "atkPro": 18,
        "lifePro": 41,
        "upgradeNum": "0_2_3_4_6_10_20_30_40_50_80",
        "upgradeGold": "0_840_1260_1680_2520_4200_8400_12600_16800_21000_33600",
        "lvLife": "645_686_727_768_809_850_891_932_973_1014",
        "lvAtk": "140_158_176_194_212_230_248_266_284_302"
    },
    {
        "id": 19,
        "name": "帕里斯",
        "raceName": "森林",
        "race": 1,
        "quality": 3,
        "attackID": 244,
        "cardFrame": 2,
        "img": "https://cdnzmg.zmfamily.cn/card/res/herov3/pls_2_19.png",
        "attack": 125,
        "life": 555,
        "skill1": 38,
        "skill2": 131,
        "skill3": 124,
        "atkPro": 20,
        "lifePro": 42,
        "upgradeNum": "0_2_3_4_6_10_20_30_40_50_80",
        "upgradeGold": "0_840_1260_1680_2520_4200_8400_12600_16800_21000_33600",
        "lvLife": "555_597_639_681_723_765_807_849_891_933",
        "lvAtk": "125_145_165_185_205_225_245_265_285_305"
    },
    {
        "id": 20,
        "name": "特普斯歌利",
        "raceName": "森林",
        "race": 1,
        "quality": 3,
        "attackID": 244,
        "cardFrame": 5,
        "img": "https://cdnzmg.zmfamily.cn/card/res/herov3/tpsgl_5_20.png",
        "attack": 135,
        "life": 600,
        "skill1": 50,
        "skill2": 123,
        "skill3": 107,
        "atkPro": 26,
        "lifePro": 17,
        "upgradeNum": "0_2_3_4_6_10_20_30_40_50_80",
        "upgradeGold": "0_840_1260_1680_2520_4200_8400_12600_16800_21000_33600",
        "lvLife": "600_617_634_651_668_685_702_719_736_753",
        "lvAtk": "135_161_187_213_239_265_291_317_343_369"
    },
    {
        "id": 21,
        "name": "乌拉妮娅",
        "raceName": "森林",
        "race": 1,
        "quality": 3,
        "attackID": 244,
        "cardFrame": 5,
        "img": "https://cdnzmg.zmfamily.cn/card/res/herov3/wlny_5_21.png",
        "attack": 215,
        "life": 800,
        "skill1": 223,
        "skill2": 83,
        "skill3": 124,
        "atkPro": 18,
        "lifePro": 39,
        "upgradeNum": "0_2_3_4_6_10_20_30_40_50_80",
        "upgradeGold": "0_840_1260_1680_2520_4200_8400_12600_16800_21000_33600",
        "lvLife": "800_839_878_917_956_995_1034_1073_1112_1151",
        "lvAtk": "215_233_251_269_287_305_323_341_359_377"
    },
    {
        "id": 22,
        "name": "阿耳刻悠妮",
        "raceName": "森林",
        "race": 1,
        "quality": 3,
        "attackID": 245,
        "cardFrame": 4,
        "img": "https://cdnzmg.zmfamily.cn/card/res/herov3/aekyn_4_22.png",
        "attack": 125,
        "life": 620,
        "skill1": 29,
        "skill2": 91,
        "skill3": 107,
        "atkPro": 24,
        "lifePro": 22,
        "upgradeNum": "0_2_3_4_6_10_20_30_40_50_80",
        "upgradeGold": "0_840_1260_1680_2520_4200_8400_12600_16800_21000_33600",
        "lvLife": "620_642_664_686_708_730_752_774_796_818",
        "lvAtk": "125_149_173_197_221_245_269_293_317_341"
    },
    {
        "id": 23,
        "name": "梅耳珀弥妮",
        "raceName": "森林",
        "race": 1,
        "quality": 4,
        "attackID": 244,
        "cardFrame": 5,
        "img": "https://cdnzmg.zmfamily.cn/card/res/herov3/mepmn_5_23.png",
        "attack": 215,
        "life": 980,
        "skill1": 20,
        "skill2": 84,
        "skill3": 125,
        "atkPro": 24,
        "lifePro": 36,
        "upgradeNum": "0_0_2_3_4_6_8_10_14_20_30",
        "upgradeGold": "0_0_3550_5325_7100_10650_14200_17750_24850_35500_53250",
        "lvLife": "980_1016_1052_1088_1124_1160_1196_1232_1268_1304",
        "lvAtk": "215_239_263_287_311_335_359_383_407_431"
    },
    {
        "id": 24,
        "name": "阿玛耳忒亚",
        "raceName": "森林",
        "race": 1,
        "quality": 4,
        "attackID": 247,
        "cardFrame": 2,
        "img": "https://cdnzmg.zmfamily.cn/card/res/herov3/amery_2_24.png",
        "attack": 195,
        "life": 800,
        "skill1": 40,
        "skill2": 98,
        "skill3": 47,
        "atkPro": 23,
        "lifePro": 39,
        "upgradeNum": "0_0_2_3_4_6_8_10_14_20_30",
        "upgradeGold": "0_0_3550_5325_7100_10650_14200_17750_24850_35500_53250",
        "lvLife": "800_839_878_917_956_995_1034_1073_1112_1151",
        "lvAtk": "195_218_241_264_287_310_333_356_379_402"
    },
    {
        "id": 25,
        "name": "塞莱诺",
        "raceName": "森林",
        "race": 1,
        "quality": 4,
        "attackID": 245,
        "cardFrame": 4,
        "img": "https://cdnzmg.zmfamily.cn/card/res/herov3/sln_4_25.png",
        "attack": 200,
        "life": 780,
        "skill1": 28,
        "skill2": 128,
        "skill3": 235,
        "atkPro": 20,
        "lifePro": 48,
        "upgradeNum": "0_0_2_3_4_6_8_10_14_20_30",
        "upgradeGold": "0_0_3550_5325_7100_10650_14200_17750_24850_35500_53250",
        "lvLife": "780_828_876_924_972_1020_1068_1116_1164_1212",
        "lvAtk": "200_220_240_260_280_300_320_340_360_380"
    },
    {
        "id": 26,
        "name": "克律塞伊丝",
        "raceName": "王国",
        "race": 2,
        "quality": 4,
        "attackID": 246,
        "cardFrame": 3,
        "img": "https://cdnzmg.zmfamily.cn/card/res/herov3/klsys_3_26.png",
        "attack": 220,
        "life": 810,
        "skill1": 52,
        "skill2": 104,
        "skill3": 59,
        "atkPro": 19,
        "lifePro": 55,
        "upgradeNum": "0_0_2_3_4_6_8_10_14_20_30",
        "upgradeGold": "0_0_3550_5325_7100_10650_14200_17750_24850_35500_53250",
        "lvLife": "810_865_920_975_1030_1085_1140_1195_1250_1305",
        "lvAtk": "220_239_258_277_296_315_334_353_372_391"
    },
    {
        "id": 27,
        "name": "泰西丝",
        "raceName": "森林",
        "race": 1,
        "quality": 4,
        "attackID": 244,
        "cardFrame": 5,
        "img": "https://cdnzmg.zmfamily.cn/card/res/herov3/txs_5_27.png",
        "attack": 270,
        "life": 1090,
        "skill1": 104,
        "skill2": 12,
        "skill3": 111,
        "atkPro": 20,
        "lifePro": 50,
        "upgradeNum": "0_0_2_3_4_6_8_10_14_20_30",
        "upgradeGold": "0_0_3550_5325_7100_10650_14200_17750_24850_35500_53250",
        "lvLife": "1090_1140_1190_1240_1290_1340_1390_1440_1490_1540",
        "lvAtk": "270_290_310_330_350_370_390_410_430_450"
    },
    {
        "id": 28,
        "name": "美杜莎",
        "raceName": "森林",
        "race": 1,
        "quality": 4,
        "attackID": 244,
        "cardFrame": 5,
        "img": "https://cdnzmg.zmfamily.cn/card/res/herov3/mds_5_28.png",
        "attack": 215,
        "life": 900,
        "skill1": 183,
        "skill2": 126,
        "skill3": 119,
        "atkPro": 15,
        "lifePro": 30,
        "upgradeNum": "0_0_2_3_4_6_8_10_14_20_30",
        "upgradeGold": "0_0_3550_5325_7100_10650_14200_17750_24850_35500_53250",
        "lvLife": "900_930_960_990_1020_1050_1080_1110_1140_1170",
        "lvAtk": "215_230_245_260_275_290_305_320_335_350"
    },
    {
        "id": 29,
        "name": "丝黛罗普",
        "raceName": "森林",
        "race": 1,
        "quality": 5,
        "attackID": 244,
        "cardFrame": 4,
        "img": "https://cdnzmg.zmfamily.cn/card/res/herov3/sdlp_4_29.png",
        "attack": 355,
        "life": 1380,
        "skill1": 243,
        "skill2": 84,
        "skill3": 204,
        "atkPro": 30,
        "lifePro": 33,
        "upgradeNum": "0_0_0_2_3_4_6_8_10_12_20",
        "upgradeGold": "0_0_0_6600_9900_13200_19800_26400_33000_39600_66000",
        "lvLife": "1380_1413_1446_1479_1512_1545_1578_1611_1644_1677",
        "lvAtk": "355_385_415_445_475_505_535_565_595_625"
    },
    {
        "id": 30,
        "name": "美狄亚",
        "raceName": "森林",
        "race": 1,
        "quality": 5,
        "attackID": 244,
        "cardFrame": 5,
        "img": "https://cdnzmg.zmfamily.cn/card/res/herov3/mdy_5_30.png",
        "attack": 340,
        "life": 1300,
        "skill1": 60,
        "skill2": 100,
        "skill3": 129,
        "atkPro": 32,
        "lifePro": 26,
        "upgradeNum": "0_0_0_2_3_4_6_8_10_12_20",
        "upgradeGold": "0_0_0_6600_9900_13200_19800_26400_33000_39600_66000",
        "lvLife": "1300_1326_1352_1378_1404_1430_1456_1482_1508_1534",
        "lvAtk": "340_372_404_436_468_500_532_564_596_628"
    },
    {
        "id": 31,
        "name": "亚岚",
        "raceName": "王国",
        "race": 2,
        "quality": 1,
        "attackID": 244,
        "cardFrame": 7,
        "img": "https://cdnzmg.zmfamily.cn/card/res/herov3/yl_7_31.png",
        "attack": 85,
        "life": 300,
        "skill1": null,
        "skill2": 81,
        "skill3": 17,
        "atkPro": 10,
        "lifePro": 36,
        "upgradeNum": "0_2_4_10_20_40_50_60_80_150",
        "upgradeGold": "0_120_240_600_1200_1800_2000_3000_3600_4800_9000",
        "lvLife": "300_336_372_408_444_480_516_552_588_624",
        "lvAtk": "85_95_105_115_125_135_145_155_165_175"
    },
    {
        "id": 32,
        "name": "普洛透斯",
        "raceName": "王国",
        "race": 2,
        "quality": 1,
        "attackID": 244,
        "cardFrame": 7,
        "img": "https://cdnzmg.zmfamily.cn/card/res/herov3/plts_7_32.png",
        "attack": 95,
        "life": 330,
        "skill1": 101,
        "skill2": 81,
        "skill3": 82,
        "atkPro": 16,
        "lifePro": 15,
        "upgradeNum": "0_2_4_10_20_40_50_60_80_150",
        "upgradeGold": "0_120_240_600_1200_1800_2000_3000_3600_4800_9000",
        "lvLife": "330_345_360_375_390_405_420_435_450_465",
        "lvAtk": "95_111_127_143_159_175_191_207_223_239"
    },
    {
        "id": 33,
        "name": "狄俄倪索斯",
        "raceName": "王国",
        "race": 2,
        "quality": 1,
        "attackID": 244,
        "cardFrame": 4,
        "img": "https://cdnzmg.zmfamily.cn/card/res/herov3/denss_4_33.png",
        "attack": 110,
        "life": 370,
        "skill1": null,
        "skill2": 102,
        "skill3": 29,
        "atkPro": 18,
        "lifePro": 8,
        "upgradeNum": "0_2_4_10_20_40_50_60_80_150",
        "upgradeGold": "0_120_240_600_1200_1800_2000_3000_3600_4800_9000",
        "lvLife": "370_378_386_394_402_410_418_426_434_442",
        "lvAtk": "110_128_146_164_182_200_218_236_254_272"
    },
    {
        "id": 34,
        "name": "克瑞斯",
        "raceName": "王国",
        "race": 2,
        "quality": 1,
        "attackID": 244,
        "cardFrame": 7,
        "img": "https://cdnzmg.zmfamily.cn/card/res/herov3/krs_7_34.png",
        "attack": 105,
        "life": 360,
        "skill1": null,
        "skill2": 17,
        "skill3": 10,
        "atkPro": 15,
        "lifePro": 21,
        "upgradeNum": "0_2_4_10_20_40_50_60_80_150",
        "upgradeGold": "0_120_240_600_1200_1800_2000_3000_3600_4800_9000",
        "lvLife": "360_381_402_423_444_465_486_507_528_549",
        "lvAtk": "105_120_135_150_165_180_195_210_225_240"
    },
    {
        "id": 35,
        "name": "伊里丝",
        "raceName": "王国",
        "race": 2,
        "quality": 1,
        "attackID": 247,
        "cardFrame": 2,
        "img": "https://cdnzmg.zmfamily.cn/card/res/herov3/yls_2_35.png",
        "attack": 80,
        "life": 285,
        "skill1": 81,
        "skill2": 49,
        "skill3": 38,
        "atkPro": 13,
        "lifePro": 27,
        "upgradeNum": "0_2_4_10_20_40_50_60_80_150",
        "upgradeGold": "0_120_240_600_1200_1800_2000_3000_3600_4800_9000",
        "lvLife": "285_312_339_366_393_420_447_474_501_528",
        "lvAtk": "80_93_106_119_132_145_158_171_184_197"
    },
    {
        "id": 36,
        "name": "涅琉斯",
        "raceName": "王国",
        "race": 2,
        "quality": 2,
        "attackID": 246,
        "cardFrame": 3,
        "img": "https://cdnzmg.zmfamily.cn/card/res/herov3/nls_3_36.png",
        "attack": 150,
        "life": 500,
        "skill1": null,
        "skill2": 102,
        "skill3": 242,
        "atkPro": 21,
        "lifePro": 19,
        "upgradeNum": "0_2_4_6_10_20_30_40_60_80_120",
        "upgradeGold": "0_330_660_990_1650_3300_4950_6600_9900_13200_19800",
        "lvLife": "500_519_538_557_576_595_614_633_652_671",
        "lvAtk": "150_171_192_213_234_255_276_297_318_339"
    },
    {
        "id": 37,
        "name": "埃阿斯",
        "raceName": "王国",
        "race": 2,
        "quality": 2,
        "attackID": 244,
        "cardFrame": 3,
        "img": "https://cdnzmg.zmfamily.cn/card/res/herov3/aas_3_37.png",
        "attack": 110,
        "life": 450,
        "skill1": 101,
        "skill2": 131,
        "skill3": 103,
        "atkPro": 19,
        "lifePro": 22,
        "upgradeNum": "0_2_4_6_10_20_30_40_60_80_120",
        "upgradeGold": "0_330_660_990_1650_3300_4950_6600_9900_13200_19800",
        "lvLife": "450_472_494_516_538_560_582_604_626_648",
        "lvAtk": "110_129_148_167_186_205_224_243_262_281"
    },
    {
        "id": 38,
        "name": "阿格莱亚",
        "raceName": "王国",
        "race": 2,
        "quality": 2,
        "attackID": 244,
        "cardFrame": 5,
        "img": "https://cdnzmg.zmfamily.cn/card/res/herov3/agly_5_38.png",
        "attack": 80,
        "life": 610,
        "skill1": 82,
        "skill2": 90,
        "skill3": 124,
        "atkPro": 9,
        "lifePro": 44,
        "upgradeNum": "0_2_4_6_10_20_30_40_60_80_120",
        "upgradeGold": "0_330_660_990_1650_3300_4950_6600_9900_13200_19800",
        "lvLife": "610_654_698_742_786_830_874_918_962_1006",
        "lvAtk": "80_89_98_107_116_125_134_143_152_161"
    },
    {
        "id": 39,
        "name": "普罗旺斯",
        "raceName": "王国",
        "race": 2,
        "quality": 2,
        "attackID": 244,
        "cardFrame": 4,
        "img": "https://cdnzmg.zmfamily.cn/card/res/herov3/plws_4_39.png",
        "attack": 155,
        "life": 500,
        "skill1": null,
        "skill2": 241,
        "skill3": 29,
        "atkPro": 21,
        "lifePro": 15,
        "upgradeNum": "0_2_4_6_10_20_30_40_60_80_120",
        "upgradeGold": "0_330_660_990_1650_3300_4950_6600_9900_13200_19800",
        "lvLife": "500_515_530_545_560_575_590_605_620_635",
        "lvAtk": "155_176_197_218_239_260_281_302_323_344"
    },
    {
        "id": 40,
        "name": "赫尔墨斯",
        "raceName": "王国",
        "race": 2,
        "quality": 2,
        "attackID": 244,
        "cardFrame": 7,
        "img": "https://cdnzmg.zmfamily.cn/card/res/herov3/hems_7_40.png",
        "attack": 160,
        "life": 520,
        "skill1": null,
        "skill2": 167,
        "skill3": 105,
        "atkPro": 22,
        "lifePro": 15,
        "upgradeNum": "0_2_4_6_10_20_30_40_60_80_120",
        "upgradeGold": "0_330_660_990_1650_3300_4950_6600_9900_13200_19800",
        "lvLife": "520_535_550_565_580_595_610_625_640_655",
        "lvAtk": "160_182_204_226_248_270_292_314_336_358"
    },
    {
        "id": 41,
        "name": "拉冬",
        "raceName": "王国",
        "race": 2,
        "quality": 2,
        "attackID": 244,
        "cardFrame": 7,
        "img": "https://cdnzmg.zmfamily.cn/card/res/herov3/ld_7_41.png",
        "attack": 135,
        "life": 500,
        "skill1": 82,
        "skill2": 10,
        "skill3": 237,
        "atkPro": 24,
        "lifePro": 9,
        "upgradeNum": "0_2_4_6_10_20_30_40_60_80_120",
        "upgradeGold": "0_330_660_990_1650_3300_4950_6600_9900_13200_19800",
        "lvLife": "500_509_518_527_536_545_554_563_572_581",
        "lvAtk": "135_159_183_207_231_255_279_303_327_351"
    },
    {
        "id": 42,
        "name": "曼妥思",
        "raceName": "王国",
        "race": 2,
        "quality": 2,
        "attackID": 244,
        "cardFrame": 5,
        "img": "https://cdnzmg.zmfamily.cn/card/res/herov3/mts_5_42.png",
        "attack": 125,
        "life": 460,
        "skill1": 90,
        "skill2": 10,
        "skill3": 95,
        "atkPro": 15,
        "lifePro": 36,
        "upgradeNum": "0_2_4_6_10_20_30_40_60_80_120",
        "upgradeGold": "0_330_660_990_1650_3300_4950_6600_9900_13200_19800",
        "lvLife": "460_496_532_568_604_640_676_712_748_784",
        "lvAtk": "125_140_155_170_185_200_215_230_245_260"
    },
    {
        "id": 43,
        "name": "尤拉诺斯",
        "raceName": "王国",
        "race": 2,
        "quality": 2,
        "attackID": 244,
        "cardFrame": 5,
        "img": "https://cdnzmg.zmfamily.cn/card/res/herov3/ylns_5_43.png",
        "attack": 110,
        "life": 400,
        "skill1": 90,
        "skill2": 82,
        "skill3": 107,
        "atkPro": 16,
        "lifePro": 34,
        "upgradeNum": "0_2_4_6_10_20_30_40_60_80_120",
        "upgradeGold": "0_330_660_990_1650_3300_4950_6600_9900_13200_19800",
        "lvLife": "400_434_468_502_536_570_604_638_672_706",
        "lvAtk": "110_126_142_158_174_190_206_222_238_254"
    },
    {
        "id": 44,
        "name": "普罗米修斯",
        "raceName": "王国",
        "race": 2,
        "quality": 3,
        "attackID": 244,
        "cardFrame": 7,
        "img": "https://cdnzmg.zmfamily.cn/card/res/herov3/plmxs_7_44.png",
        "attack": 125,
        "life": 820,
        "skill1": 115,
        "skill2": 82,
        "skill3": 201,
        "atkPro": 10,
        "lifePro": 42,
        "upgradeNum": "0_2_3_4_6_10_20_30_40_50_80",
        "upgradeGold": "0_840_1260_1680_2520_4200_8400_12600_16800_21000_33600",
        "lvLife": "820_862_904_946_988_1030_1072_1114_1156_1198",
        "lvAtk": "125_135_145_155_165_175_185_195_205_215"
    },
    {
        "id": 45,
        "name": "雅典娜",
        "raceName": "王国",
        "race": 2,
        "quality": 3,
        "attackID": 244,
        "cardFrame": 7,
        "img": "https://cdnzmg.zmfamily.cn/card/res/herov3/ydn_7_45.png",
        "attack": 180,
        "life": 620,
        "skill1": 240,
        "skill2": 201,
        "skill3": 10,
        "atkPro": 20,
        "lifePro": 25,
        "upgradeNum": "0_2_3_4_6_10_20_30_40_50_80",
        "upgradeGold": "0_840_1260_1680_2520_4200_8400_12600_16800_21000_33600",
        "lvLife": "620_645_670_695_720_745_770_795_820_845",
        "lvAtk": "180_200_220_240_260_280_300_320_340_360"
    },
    {
        "id": 46,
        "name": "瑞亚",
        "raceName": "王国",
        "race": 2,
        "quality": 3,
        "attackID": 246,
        "cardFrame": 3,
        "img": "https://cdnzmg.zmfamily.cn/card/res/herov3/ry_3_46.png",
        "attack": 200,
        "life": 780,
        "skill1": 225,
        "skill2": 83,
        "skill3": 188,
        "atkPro": 23,
        "lifePro": 25,
        "upgradeNum": "0_2_3_4_6_10_20_30_40_50_80",
        "upgradeGold": "0_840_1260_1680_2520_4200_8400_12600_16800_21000_33600",
        "lvLife": "780_805_830_855_880_905_930_955_980_1005",
        "lvAtk": "200_223_246_269_292_315_338_361_384_407"
    },
    {
        "id": 47,
        "name": "俄琉斯",
        "raceName": "王国",
        "race": 2,
        "quality": 3,
        "attackID": 246,
        "cardFrame": 3,
        "img": "https://cdnzmg.zmfamily.cn/card/res/herov3/els_3_47.png",
        "attack": 140,
        "life": 620,
        "skill1": 49,
        "skill2": 200,
        "skill3": 55,
        "atkPro": 20,
        "lifePro": 37,
        "upgradeNum": "0_2_3_4_6_10_20_30_40_50_80",
        "upgradeGold": "0_840_1260_1680_2520_4200_8400_12600_16800_21000_33600",
        "lvLife": "620_657_694_731_768_805_842_879_916_953",
        "lvAtk": "140_160_180_200_220_240_260_280_300_320"
    },
    {
        "id": 48,
        "name": "潘",
        "raceName": "王国",
        "race": 2,
        "quality": 3,
        "attackID": 244,
        "cardFrame": 4,
        "img": "https://cdnzmg.zmfamily.cn/card/res/herov3/pan_4_48.png",
        "attack": 185,
        "life": 650,
        "skill1": 241,
        "skill2": 30,
        "skill3": 107,
        "atkPro": 21,
        "lifePro": 30,
        "upgradeNum": "0_2_3_4_6_10_20_30_40_50_80",
        "upgradeGold": "0_840_1260_1680_2520_4200_8400_12600_16800_21000_33600",
        "lvLife": "650_680_710_740_770_800_830_860_890_920",
        "lvAtk": "185_206_227_248_269_290_311_332_353_374"
    },
    {
        "id": 49,
        "name": "塔吉忒",
        "raceName": "王国",
        "race": 2,
        "quality": 3,
        "attackID": 245,
        "cardFrame": 4,
        "img": "https://cdnzmg.zmfamily.cn/card/res/herov3/tjr_4_49.png",
        "attack": 135,
        "life": 560,
        "skill1": 53,
        "skill2": 206,
        "skill3": 31,
        "atkPro": 24,
        "lifePro": 21,
        "upgradeNum": "0_2_3_4_6_10_20_30_40_50_80",
        "upgradeGold": "0_840_1260_1680_2520_4200_8400_12600_16800_21000_33600",
        "lvLife": "560_581_602_623_644_665_686_707_728_749",
        "lvAtk": "135_159_183_207_231_255_279_303_327_351"
    },
    {
        "id": 50,
        "name": "拉奥孔",
        "raceName": "王国",
        "race": 2,
        "quality": 3,
        "attackID": 245,
        "cardFrame": 4,
        "img": "https://cdnzmg.zmfamily.cn/card/res/herov3/lak_4_50.png",
        "attack": 195,
        "life": 650,
        "skill1": 209,
        "skill2": 127,
        "skill3": 10,
        "atkPro": 19,
        "lifePro": 30,
        "upgradeNum": "0_2_3_4_6_10_20_30_40_50_80",
        "upgradeGold": "0_840_1260_1680_2520_4200_8400_12600_16800_21000_33600",
        "lvLife": "650_680_710_740_770_800_830_860_890_920",
        "lvAtk": "195_214_233_252_271_290_309_328_347_366"
    },
    {
        "id": 51,
        "name": "塔利亚",
        "raceName": "王国",
        "race": 2,
        "quality": 3,
        "attackID": 244,
        "cardFrame": 5,
        "img": "https://cdnzmg.zmfamily.cn/card/res/herov3/tly_5_51.png",
        "attack": 175,
        "life": 750,
        "skill1": 90,
        "skill2": 108,
        "skill3": 115,
        "atkPro": 22,
        "lifePro": 31,
        "upgradeNum": "0_2_3_4_6_10_20_30_40_50_80",
        "upgradeGold": "0_840_1260_1680_2520_4200_8400_12600_16800_21000_33600",
        "lvLife": "750_781_812_843_874_905_936_967_998_1029",
        "lvAtk": "175_197_219_241_263_285_307_329_351_373"
    },
    {
        "id": 52,
        "name": "辛尼斯",
        "raceName": "王国",
        "race": 2,
        "quality": 3,
        "attackID": 244,
        "cardFrame": 2,
        "img": "https://cdnzmg.zmfamily.cn/card/res/herov3/xns_2_52.png",
        "attack": 130,
        "life": 550,
        "skill1": 43,
        "skill2": 214,
        "skill3": 131,
        "atkPro": 16,
        "lifePro": 40,
        "upgradeNum": "0_2_3_4_6_10_20_30_40_50_80",
        "upgradeGold": "0_840_1260_1680_2520_4200_8400_12600_16800_21000_33600",
        "lvLife": "550_590_630_670_710_750_790_830_870_910",
        "lvAtk": "130_146_162_178_194_210_226_242_258_274"
    },
    {
        "id": 53,
        "name": "狄安娜",
        "raceName": "王国",
        "race": 2,
        "quality": 4,
        "attackID": 246,
        "cardFrame": 3,
        "img": "https://cdnzmg.zmfamily.cn/card/res/herov3/dan_3_53.png",
        "attack": 235,
        "life": 880,
        "skill1": 84,
        "skill2": 243,
        "skill3": 112,
        "atkPro": 28,
        "lifePro": 23,
        "upgradeNum": "0_0_2_3_4_6_8_10_14_20_30",
        "upgradeGold": "0_0_3550_5325_7100_10650_14200_17750_24850_35500_53250",
        "lvLife": "880_903_926_949_972_995_1018_1041_1064_1087",
        "lvAtk": "235_263_291_319_347_375_403_431_459_487"
    },
    {
        "id": 54,
        "name": "菲碧",
        "raceName": "王国",
        "race": 2,
        "quality": 4,
        "attackID": 247,
        "cardFrame": 2,
        "img": "https://cdnzmg.zmfamily.cn/card/res/herov3/fb_2_54.png",
        "attack": 175,
        "life": 800,
        "skill1": 99,
        "skill2": 98,
        "skill3": 120,
        "atkPro": 15,
        "lifePro": 66,
        "upgradeNum": "0_0_2_3_4_6_8_10_14_20_30",
        "upgradeGold": "0_0_3550_5325_7100_10650_14200_17750_24850_35500_53250",
        "lvLife": "800_866_932_998_1064_1130_1196_1262_1328_1394",
        "lvAtk": "175_190_205_220_235_250_265_280_295_310"
    },
    {
        "id": 55,
        "name": "托尔",
        "raceName": "王国",
        "race": 2,
        "quality": 4,
        "attackID": 244,
        "cardFrame": 4,
        "img": "https://cdnzmg.zmfamily.cn/card/res/herov3/te_4_55.png",
        "attack": 260,
        "life": 1100,
        "skill1": 203,
        "skill2": 109,
        "skill3": 12,
        "atkPro": 40,
        "lifePro": 30,
        "upgradeNum": "0_0_2_3_4_6_8_10_14_20_30",
        "upgradeGold": "0_0_3550_5325_7100_10650_14200_17750_24850_35500_53250",
        "lvLife": "1100_1130_1160_1190_1220_1250_1280_1310_1340_1370",
        "lvAtk": "260_300_340_380_420_460_500_540_580_620"
    },
    {
        "id": 56,
        "name": "海泼里恩",
        "raceName": "王国",
        "race": 2,
        "quality": 4,
        "attackID": 244,
        "cardFrame": 5,
        "img": "https://cdnzmg.zmfamily.cn/card/res/herov3/hpln_5_56.png",
        "attack": 210,
        "life": 790,
        "skill1": 92,
        "skill2": 56,
        "skill3": 180,
        "atkPro": 24,
        "lifePro": 37,
        "upgradeNum": "0_0_2_3_4_6_8_10_14_20_30",
        "upgradeGold": "0_0_3550_5325_7100_10650_14200_17750_24850_35500_53250",
        "lvLife": "790_827_864_901_938_975_1012_1049_1086_1123",
        "lvAtk": "210_234_258_282_306_330_354_378_402_426"
    },
    {
        "id": 57,
        "name": "缪斯",
        "raceName": "王国",
        "race": 2,
        "quality": 4,
        "attackID": 244,
        "cardFrame": 5,
        "img": "https://cdnzmg.zmfamily.cn/card/res/herov3/ls_5_57.png",
        "attack": 290,
        "life": 990,
        "skill1": 168,
        "skill2": 11,
        "skill3": 125,
        "atkPro": 18,
        "lifePro": 58,
        "upgradeNum": "0_0_2_3_4_6_8_10_14_20_30",
        "upgradeGold": "0_0_3550_5325_7100_10650_14200_17750_24850_35500_53250",
        "lvLife": "990_1048_1106_1164_1222_1280_1338_1396_1454_1512",
        "lvAtk": "290_308_326_344_362_380_398_416_434_452"
    },
    {
        "id": 58,
        "name": "维纳斯",
        "raceName": "王国",
        "race": 2,
        "quality": 4,
        "attackID": 246,
        "cardFrame": 3,
        "img": "https://cdnzmg.zmfamily.cn/card/res/herov3/wns_3_58.png",
        "attack": 260,
        "life": 815,
        "skill1": 242,
        "skill2": 104,
        "skill3": 239,
        "atkPro": 30,
        "lifePro": 18,
        "upgradeNum": "0_0_2_3_4_6_8_10_14_20_30",
        "upgradeGold": "0_0_3550_5325_7100_10650_14200_17750_24850_35500_53250",
        "lvLife": "815_833_851_869_887_905_923_941_959_977",
        "lvAtk": "260_290_320_350_380_410_440_470_500_530"
    },
    {
        "id": 59,
        "name": "阿伽门农",
        "raceName": "王国",
        "race": 2,
        "quality": 5,
        "attackID": 244,
        "cardFrame": 2,
        "img": "https://cdnzmg.zmfamily.cn/card/res/herov3/ajmn_2_59.png",
        "attack": 365,
        "life": 1500,
        "skill1": 202,
        "skill2": 185,
        "skill3": 100,
        "atkPro": 24,
        "lifePro": 54,
        "upgradeNum": "0_0_0_2_3_4_6_8_10_12_20",
        "upgradeGold": "0_0_0_6600_9900_13200_19800_26400_33000_39600_66000",
        "lvLife": "1500_1554_1608_1662_1716_1770_1824_1878_1932_1986",
        "lvAtk": "365_389_413_437_461_485_509_533_557_581"
    },
    {
        "id": 60,
        "name": "欧罗巴",
        "raceName": "王国",
        "race": 2,
        "quality": 5,
        "attackID": 244,
        "cardFrame": 5,
        "img": "https://cdnzmg.zmfamily.cn/card/res/herov3/olb_5_60.png",
        "attack": 350,
        "life": 1350,
        "skill1": 239,
        "skill2": 105,
        "skill3": 204,
        "atkPro": 28,
        "lifePro": 38,
        "upgradeNum": "0_0_0_2_3_4_6_8_10_12_20",
        "upgradeGold": "0_0_0_6600_9900_13200_19800_26400_33000_39600_66000",
        "lvLife": "1350_1388_1426_1464_1502_1540_1578_1616_1654_1692",
        "lvAtk": "350_378_406_434_462_490_518_546_574_602"
    },
    {
        "id": 61,
        "name": "塞壬",
        "raceName": "蛮荒",
        "race": 3,
        "quality": 1,
        "attackID": 244,
        "cardFrame": 2,
        "img": "https://cdnzmg.zmfamily.cn/card/res/herov3/sr_2_61.png",
        "attack": 90,
        "life": 390,
        "skill1": null,
        "skill2": 102,
        "skill3": 38,
        "atkPro": 18,
        "lifePro": 11,
        "upgradeNum": "0_2_4_10_20_40_50_60_80_150",
        "upgradeGold": "0_120_240_600_1200_1800_2000_3000_3600_4800_9000",
        "lvLife": "390_401_412_423_434_445_456_467_478_489",
        "lvAtk": "90_108_126_144_162_180_198_216_234_252"
    },
    {
        "id": 62,
        "name": "伊丽莎白",
        "raceName": "蛮荒",
        "race": 3,
        "quality": 1,
        "attackID": 244,
        "cardFrame": 7,
        "img": "https://cdnzmg.zmfamily.cn/card/res/herov3/ylsb_7_62.png",
        "attack": 95,
        "life": 360,
        "skill1": null,
        "skill2": 10,
        "skill3": 168,
        "atkPro": 15,
        "lifePro": 20,
        "upgradeNum": "0_2_4_10_20_40_50_60_80_150",
        "upgradeGold": "0_120_240_600_1200_1800_2000_3000_3600_4800_9000",
        "lvLife": "360_380_400_420_440_460_480_500_520_540",
        "lvAtk": "95_110_125_140_155_170_185_200_215_230"
    },
    {
        "id": 63,
        "name": "杰西卡",
        "raceName": "蛮荒",
        "race": 3,
        "quality": 1,
        "attackID": 244,
        "cardFrame": 1,
        "img": "https://cdnzmg.zmfamily.cn/card/res/herov3/jxk_1_63.png",
        "attack": 75,
        "life": 280,
        "skill1": 69,
        "skill2": 17,
        "skill3": 241,
        "atkPro": 16,
        "lifePro": 17,
        "upgradeNum": "0_2_4_10_20_40_50_60_80_150",
        "upgradeGold": "0_120_240_600_1200_1800_2000_3000_3600_4800_9000",
        "lvLife": "280_297_314_331_348_365_382_399_416_433",
        "lvAtk": "75_91_107_123_139_155_171_187_203_219"
    },
    {
        "id": 64,
        "name": "芙蓉",
        "raceName": "蛮荒",
        "race": 3,
        "quality": 1,
        "attackID": 248,
        "cardFrame": 6,
        "img": "https://cdnzmg.zmfamily.cn/card/res/herov3/fr_6_64.png",
        "attack": 95,
        "life": 275,
        "skill1": 1,
        "skill2": 102,
        "skill3": 74,
        "atkPro": 19,
        "lifePro": 6,
        "upgradeNum": "0_2_4_10_20_40_50_60_80_150",
        "upgradeGold": "0_120_240_600_1200_1800_2000_3000_3600_4800_9000",
        "lvLife": "275_281_287_293_299_305_311_317_323_329",
        "lvAtk": "95_114_133_152_171_190_209_228_247_266"
    },
    {
        "id": 65,
        "name": "多丽斯",
        "raceName": "蛮荒",
        "race": 3,
        "quality": 1,
        "attackID": 244,
        "cardFrame": 4,
        "img": "https://cdnzmg.zmfamily.cn/card/res/herov3/dls_4_65.png",
        "attack": 90,
        "life": 310,
        "skill1": null,
        "skill2": 17,
        "skill3": 30,
        "atkPro": 15,
        "lifePro": 18,
        "upgradeNum": "0_2_4_10_20_40_50_60_80_150",
        "upgradeGold": "0_120_240_600_1200_1800_2000_3000_3600_4800_9000",
        "lvLife": "310_328_346_364_382_400_418_436_454_472",
        "lvAtk": "90_105_120_135_150_165_180_195_210_225"
    },
    {
        "id": 66,
        "name": "泰西丝",
        "raceName": "蛮荒",
        "race": 3,
        "quality": 2,
        "attackID": 244,
        "cardFrame": 7,
        "img": "https://cdnzmg.zmfamily.cn/card/res/herov3/txs_7_66.png",
        "attack": 110,
        "life": 430,
        "skill1": 240,
        "skill2": 82,
        "skill3": 103,
        "atkPro": 24,
        "lifePro": 7,
        "upgradeNum": "0_2_4_6_10_20_30_40_60_80_120",
        "upgradeGold": "0_330_660_990_1650_3300_4950_6600_9900_13200_19800",
        "lvLife": "430_437_444_451_458_465_472_479_486_493",
        "lvAtk": "110_134_158_182_206_230_254_278_302_326"
    },
    {
        "id": 67,
        "name": "忒提丝",
        "raceName": "蛮荒",
        "race": 3,
        "quality": 2,
        "attackID": 244,
        "cardFrame": 6,
        "img": "https://cdnzmg.zmfamily.cn/card/res/herov3/rts_6_67.png",
        "attack": 200,
        "life": 510,
        "skill1": 61,
        "skill2": 7,
        "skill3": 171,
        "atkPro": 20,
        "lifePro": 20,
        "upgradeNum": "0_2_4_6_10_20_30_40_60_80_120",
        "upgradeGold": "0_330_660_990_1650_3300_4950_6600_9900_13200_19800",
        "lvLife": "510_530_550_570_590_610_630_650_670_690",
        "lvAtk": "200_220_240_260_280_300_320_340_360_380"
    },
    {
        "id": 68,
        "name": "德克斯",
        "raceName": "蛮荒",
        "race": 3,
        "quality": 2,
        "attackID": 244,
        "cardFrame": 7,
        "img": "https://cdnzmg.zmfamily.cn/card/res/herov3/dks_7_68.png",
        "attack": 160,
        "life": 475,
        "skill1": null,
        "skill2": 82,
        "skill3": 11,
        "atkPro": 24,
        "lifePro": 5,
        "upgradeNum": "0_2_4_6_10_20_30_40_60_80_120",
        "upgradeGold": "0_330_660_990_1650_3300_4950_6600_9900_13200_19800",
        "lvLife": "475_480_485_490_495_500_505_510_515_520",
        "lvAtk": "160_184_208_232_256_280_304_328_352_376"
    },
    {
        "id": 69,
        "name": "堤丰",
        "raceName": "蛮荒",
        "race": 3,
        "quality": 2,
        "attackID": 244,
        "cardFrame": 7,
        "img": "https://cdnzmg.zmfamily.cn/card/res/herov3/df_7_69.png",
        "attack": 135,
        "life": 490,
        "skill1": 2,
        "skill2": 102,
        "skill3": 237,
        "atkPro": 23,
        "lifePro": 13,
        "upgradeNum": "0_2_4_6_10_20_30_40_60_80_120",
        "upgradeGold": "0_330_660_990_1650_3300_4950_6600_9900_13200_19800",
        "lvLife": "490_503_516_529_542_555_568_581_594_607",
        "lvAtk": "135_158_181_204_227_250_273_296_319_342"
    },
    {
        "id": 70,
        "name": "海精",
        "raceName": "蛮荒",
        "race": 3,
        "quality": 2,
        "attackID": 248,
        "cardFrame": 6,
        "img": "https://cdnzmg.zmfamily.cn/card/res/herov3/hj_6_70.png",
        "attack": 165,
        "life": 550,
        "skill1": null,
        "skill2": 163,
        "skill3": 168,
        "atkPro": 17,
        "lifePro": 29,
        "upgradeNum": "0_2_4_6_10_20_30_40_60_80_120",
        "upgradeGold": "0_330_660_990_1650_3300_4950_6600_9900_13200_19800",
        "lvLife": "550_579_608_637_666_695_724_753_782_811",
        "lvAtk": "165_182_199_216_233_250_267_284_301_318"
    },
    {
        "id": 71,
        "name": "厄洛斯",
        "raceName": "蛮荒",
        "race": 3,
        "quality": 2,
        "attackID": 244,
        "cardFrame": 1,
        "img": "https://cdnzmg.zmfamily.cn/card/res/herov3/els_1_71.png",
        "attack": 110,
        "life": 450,
        "skill1": 69,
        "skill2": 154,
        "skill3": 107,
        "atkPro": 24,
        "lifePro": 18,
        "upgradeNum": "0_2_4_6_10_20_30_40_60_80_120",
        "upgradeGold": "0_330_660_990_1650_3300_4950_6600_9900_13200_19800",
        "lvLife": "450_468_486_504_522_540_558_576_594_612",
        "lvAtk": "110_134_158_182_206_230_254_278_302_326"
    },
    {
        "id": 72,
        "name": "克拉托斯",
        "raceName": "蛮荒",
        "race": 3,
        "quality": 2,
        "attackID": 244,
        "cardFrame": 7,
        "img": "https://cdnzmg.zmfamily.cn/card/res/herov3/klsts_7_72.png",
        "attack": 135,
        "life": 510,
        "skill1": 81,
        "skill2": 10,
        "skill3": 124,
        "atkPro": 24,
        "lifePro": 7,
        "upgradeNum": "0_2_4_6_10_20_30_40_60_80_120",
        "upgradeGold": "0_330_660_990_1650_3300_4950_6600_9900_13200_19800",
        "lvLife": "510_517_524_531_538_545_552_559_566_573",
        "lvAtk": "135_159_183_207_231_255_279_303_327_351"
    },
    {
        "id": 73,
        "name": "卡特琳",
        "raceName": "蛮荒",
        "race": 3,
        "quality": 2,
        "attackID": 244,
        "cardFrame": 1,
        "img": "https://cdnzmg.zmfamily.cn/card/res/herov3/ktl_1_73.png",
        "attack": 135,
        "life": 440,
        "skill1": 147,
        "skill2": 10,
        "skill3": 156,
        "atkPro": 24,
        "lifePro": 10,
        "upgradeNum": "0_2_4_6_10_20_30_40_60_80_120",
        "upgradeGold": "0_330_660_990_1650_3300_4950_6600_9900_13200_19800",
        "lvLife": "440_450_460_470_480_490_500_510_520_530",
        "lvAtk": "135_159_183_207_231_255_279_303_327_351"
    },
    {
        "id": 74,
        "name": "潘多拉",
        "raceName": "蛮荒",
        "race": 3,
        "quality": 3,
        "attackID": 248,
        "cardFrame": 6,
        "img": "https://cdnzmg.zmfamily.cn/card/res/herov3/pdl_6_74.png",
        "attack": 140,
        "life": 685,
        "skill1": 73,
        "skill2": 103,
        "skill3": 17,
        "atkPro": 26,
        "lifePro": 20,
        "upgradeNum": "0_2_3_4_6_10_20_30_40_50_80",
        "upgradeGold": "0_840_1260_1680_2520_4200_8400_12600_16800_21000_33600",
        "lvLife": "685_705_725_745_765_785_805_825_845_865",
        "lvAtk": "140_166_192_218_244_270_296_322_348_374"
    },
    {
        "id": 75,
        "name": "安娜",
        "raceName": "蛮荒",
        "race": 3,
        "quality": 3,
        "attackID": 244,
        "cardFrame": 7,
        "img": "https://cdnzmg.zmfamily.cn/card/res/herov3/an_7_75.png",
        "attack": 175,
        "life": 720,
        "skill1": 81,
        "skill2": 168,
        "skill3": 124,
        "atkPro": 25,
        "lifePro": 17,
        "upgradeNum": "0_2_3_4_6_10_20_30_40_50_80",
        "upgradeGold": "0_840_1260_1680_2520_4200_8400_12600_16800_21000_33600",
        "lvLife": "720_737_754_771_788_805_822_839_856_873",
        "lvAtk": "175_200_225_250_275_300_325_350_375_400"
    },
    {
        "id": 76,
        "name": "厄瑞涅",
        "raceName": "蛮荒",
        "race": 3,
        "quality": 3,
        "attackID": 248,
        "cardFrame": 6,
        "img": "https://cdnzmg.zmfamily.cn/card/res/herov3/ern_6_76.png",
        "attack": 125,
        "life": 650,
        "skill1": 53,
        "skill2": 135,
        "skill3": 107,
        "atkPro": 19,
        "lifePro": 39,
        "upgradeNum": "0_2_3_4_6_10_20_30_40_50_80",
        "upgradeGold": "0_840_1260_1680_2520_4200_8400_12600_16800_21000_33600",
        "lvLife": "650_689_728_767_806_845_884_923_962_1001",
        "lvAtk": "125_144_163_182_201_220_239_258_277_296"
    },
    {
        "id": 77,
        "name": "赫淮斯托斯",
        "raceName": "蛮荒",
        "race": 3,
        "quality": 3,
        "attackID": 246,
        "cardFrame": 3,
        "img": "https://cdnzmg.zmfamily.cn/card/res/herov3/hhsts_3_77.png",
        "attack": 205,
        "life": 730,
        "skill1": 225,
        "skill2": 163,
        "skill3": 242,
        "atkPro": 28,
        "lifePro": 9,
        "upgradeNum": "0_2_3_4_6_10_20_30_40_50_80",
        "upgradeGold": "0_840_1260_1680_2520_4200_8400_12600_16800_21000_33600",
        "lvLife": "730_739_748_757_766_775_784_793_802_811",
        "lvAtk": "205_233_261_289_317_345_373_401_429_457"
    },
    {
        "id": 78,
        "name": "欧诺弥亚",
        "raceName": "蛮荒",
        "race": 3,
        "quality": 3,
        "attackID": 248,
        "cardFrame": 6,
        "img": "https://cdnzmg.zmfamily.cn/card/res/herov3/onmy_6_78.png",
        "attack": 115,
        "life": 550,
        "skill1": 50,
        "skill2": 155,
        "skill3": 192,
        "atkPro": 23,
        "lifePro": 25,
        "upgradeNum": "0_2_3_4_6_10_20_30_40_50_80",
        "upgradeGold": "0_840_1260_1680_2520_4200_8400_12600_16800_21000_33600",
        "lvLife": "550_575_600_625_650_675_700_725_750_775",
        "lvAtk": "115_138_161_184_207_230_253_276_299_322"
    },
    {
        "id": 79,
        "name": "珀耳塞",
        "raceName": "蛮荒",
        "race": 3,
        "quality": 3,
        "attackID": 247,
        "cardFrame": 2,
        "img": "https://cdnzmg.zmfamily.cn/card/res/herov3/pes_2_79.png",
        "attack": 175,
        "life": 580,
        "skill1": 205,
        "skill2": 51,
        "skill3": 95,
        "atkPro": 25,
        "lifePro": 20,
        "upgradeNum": "0_2_3_4_6_10_20_30_40_50_80",
        "upgradeGold": "0_840_1260_1680_2520_4200_8400_12600_16800_21000_33600",
        "lvLife": "580_600_620_640_660_680_700_720_740_760",
        "lvAtk": "175_200_225_250_275_300_325_350_375_400"
    },
    {
        "id": 80,
        "name": "涅柔斯",
        "raceName": "蛮荒",
        "race": 3,
        "quality": 3,
        "attackID": 248,
        "cardFrame": 6,
        "img": "https://cdnzmg.zmfamily.cn/card/res/herov3/nrs_6_80.png",
        "attack": 185,
        "life": 630,
        "skill1": 162,
        "skill2": 123,
        "skill3": 83,
        "atkPro": 27,
        "lifePro": 17,
        "upgradeNum": "0_2_3_4_6_10_20_30_40_50_80",
        "upgradeGold": "0_840_1260_1680_2520_4200_8400_12600_16800_21000_33600",
        "lvLife": "630_647_664_681_698_715_732_749_766_783",
        "lvAtk": "185_212_239_266_293_320_347_374_401_428"
    },
    {
        "id": 81,
        "name": "美狄亚",
        "raceName": "蛮荒",
        "race": 3,
        "quality": 3,
        "attackID": 244,
        "cardFrame": 2,
        "img": "https://cdnzmg.zmfamily.cn/card/res/herov3/mdy_2_81.png",
        "attack": 190,
        "life": 690,
        "skill1": 240,
        "skill2": 214,
        "skill3": 115,
        "atkPro": 18,
        "lifePro": 41,
        "upgradeNum": "0_2_3_4_6_10_20_30_40_50_80",
        "upgradeGold": "0_840_1260_1680_2520_4200_8400_12600_16800_21000_33600",
        "lvLife": "690_731_772_813_854_895_936_977_1018_1059",
        "lvAtk": "190_208_226_244_262_280_298_316_334_352"
    },
    {
        "id": 82,
        "name": "珀耳塞福涅",
        "raceName": "地狱",
        "race": 4,
        "quality": 3,
        "attackID": 244,
        "cardFrame": 1,
        "img": "https://cdnzmg.zmfamily.cn/card/res/herov3/pesfn_1_82.png",
        "attack": 180,
        "life": 615,
        "skill1": 146,
        "skill2": 71,
        "skill3": 11,
        "atkPro": 30,
        "lifePro": 20,
        "upgradeNum": "0_2_3_4_6_10_20_30_40_50_80",
        "upgradeGold": "0_840_1260_1680_2520_4200_8400_12600_16800_21000_33600",
        "lvLife": "615_635_655_675_695_715_735_755_775_795",
        "lvAtk": "180_210_240_270_300_330_360_390_420_450"
    },
    {
        "id": 83,
        "name": "卡捷琳娜",
        "raceName": "蛮荒",
        "race": 3,
        "quality": 4,
        "attackID": 244,
        "cardFrame": 7,
        "img": "https://cdnzmg.zmfamily.cn/card/res/herov3/kjln_7_83.png",
        "attack": 245,
        "life": 840,
        "skill1": 11,
        "skill2": 104,
        "skill3": 111,
        "atkPro": 20,
        "lifePro": 52,
        "upgradeNum": "0_0_2_3_4_6_8_10_14_20_30",
        "upgradeGold": "0_0_3550_5325_7100_10650_14200_17750_24850_35500_53250",
        "lvLife": "840_892_944_996_1048_1100_1152_1204_1256_1308",
        "lvAtk": "245_265_285_305_325_345_365_385_405_425"
    },
    {
        "id": 84,
        "name": "阿穆芙莱特",
        "raceName": "蛮荒",
        "race": 3,
        "quality": 4,
        "attackID": 248,
        "cardFrame": 6,
        "img": "https://cdnzmg.zmfamily.cn/card/res/herov3/amflt_6_84.png",
        "attack": 250,
        "life": 890,
        "skill1": 148,
        "skill2": 12,
        "skill3": 165,
        "atkPro": 22,
        "lifePro": 45,
        "upgradeNum": "0_0_2_3_4_6_8_10_14_20_30",
        "upgradeGold": "0_0_3550_5325_7100_10650_14200_17750_24850_35500_53250",
        "lvLife": "890_935_980_1025_1070_1115_1160_1205_1250_1295",
        "lvAtk": "250_272_294_316_338_360_382_404_426_448"
    },
    {
        "id": 85,
        "name": "赫利俄斯",
        "raceName": "蛮荒",
        "race": 3,
        "quality": 4,
        "attackID": 244,
        "cardFrame": 3,
        "img": "https://cdnzmg.zmfamily.cn/card/res/herov3/hles_3_85.png",
        "attack": 255,
        "life": 850,
        "skill1": 242,
        "skill2": 87,
        "skill3": 119,
        "atkPro": 30,
        "lifePro": 20,
        "upgradeNum": "0_0_2_3_4_6_8_10_14_20_30",
        "upgradeGold": "0_0_3550_5325_7100_10650_14200_17750_24850_35500_53250",
        "lvLife": "850_870_890_910_930_950_970_990_1010_1030",
        "lvAtk": "255_285_315_345_375_405_435_465_495_525"
    },
    {
        "id": 86,
        "name": "玉藻前",
        "raceName": "蛮荒",
        "race": 3,
        "quality": 4,
        "attackID": 246,
        "cardFrame": 3,
        "img": "https://cdnzmg.zmfamily.cn/card/res/herov3/yzq_3_86.png",
        "attack": 250,
        "life": 980,
        "skill1": 231,
        "skill2": 105,
        "skill3": 182,
        "atkPro": 10,
        "lifePro": 20,
        "upgradeNum": "0_0_2_3_4_6_8_10_14_20_30",
        "upgradeGold": "0_0_3550_5325_7100_10650_14200_17750_24850_35500_53250",
        "lvLife": "980_1000_1020_1040_1060_1080_1100_1120_1140_1160",
        "lvAtk": "250_260_270_280_290_300_310_320_330_340"
    },
    {
        "id": 87,
        "name": "绪任克斯",
        "raceName": "蛮荒",
        "race": 3,
        "quality": 4,
        "attackID": 244,
        "cardFrame": 7,
        "img": "https://cdnzmg.zmfamily.cn/card/res/herov3/xrks_7_87.png",
        "attack": 285,
        "life": 1230,
        "skill1": 83,
        "skill2": 12,
        "skill3": 198,
        "atkPro": 21,
        "lifePro": 47,
        "upgradeNum": "0_0_2_3_4_6_8_10_14_20_30",
        "upgradeGold": "0_0_3550_5325_7100_10650_14200_17750_24850_35500_53250",
        "lvLife": "1230_1277_1324_1371_1418_1465_1512_1559_1606_1653",
        "lvAtk": "285_306_327_348_369_390_411_432_453_474"
    },
    {
        "id": 88,
        "name": "伊西斯",
        "raceName": "蛮荒",
        "race": 3,
        "quality": 4,
        "attackID": 244,
        "cardFrame": 2,
        "img": "https://cdnzmg.zmfamily.cn/card/res/herov3/yxs_2_88.png",
        "attack": 245,
        "life": 900,
        "skill1": 12,
        "skill2": 169,
        "skill3": 196,
        "atkPro": 25,
        "lifePro": 32,
        "upgradeNum": "0_0_2_3_4_6_8_10_14_20_30",
        "upgradeGold": "0_0_3550_5325_7100_10650_14200_17750_24850_35500_53250",
        "lvLife": "900_932_964_996_1028_1060_1092_1124_1156_1188",
        "lvAtk": "245_270_295_320_345_370_395_420_445_470"
    },
    {
        "id": 89,
        "name": "彭透斯",
        "raceName": "蛮荒",
        "race": 3,
        "quality": 5,
        "attackID": 245,
        "cardFrame": 4,
        "img": "https://cdnzmg.zmfamily.cn/card/res/herov3/pts_4_89.png",
        "attack": 340,
        "life": 1200,
        "skill1": 36,
        "skill2": 12,
        "skill3": 204,
        "atkPro": 20,
        "lifePro": 35,
        "upgradeNum": "0_0_0_2_3_4_6_8_10_12_20",
        "upgradeGold": "0_0_0_6600_9900_13200_19800_26400_33000_39600_66000",
        "lvLife": "1200_1235_1270_1305_1340_1375_1410_1445_1480_1515",
        "lvAtk": "340_360_380_400_420_440_460_480_500_520"
    },
    {
        "id": 90,
        "name": "喀迈拉",
        "raceName": "蛮荒",
        "race": 3,
        "quality": 5,
        "attackID": 244,
        "cardFrame": 2,
        "img": "https://cdnzmg.zmfamily.cn/card/res/herov3/kml_2_90.png",
        "attack": 335,
        "life": 1330,
        "skill1": 48,
        "skill2": 80,
        "skill3": 125,
        "atkPro": 33,
        "lifePro": 25,
        "upgradeNum": "0_0_0_2_3_4_6_8_10_12_20",
        "upgradeGold": "0_0_0_6600_9900_13200_19800_26400_33000_39600_66000",
        "lvLife": "1330_1355_1380_1405_1430_1455_1480_1505_1530_1555",
        "lvAtk": "335_368_401_434_467_500_533_566_599_632"
    },
    {
        "id": 91,
        "name": "洛狄忒",
        "raceName": "地狱",
        "race": 4,
        "quality": 1,
        "attackID": 246,
        "cardFrame": 3,
        "img": "https://cdnzmg.zmfamily.cn/card/res/herov3/ldr_3_91.png",
        "attack": 80,
        "life": 270,
        "skill1": 49,
        "skill2": 74,
        "skill3": 50,
        "atkPro": 19,
        "lifePro": 6,
        "upgradeNum": "0_2_4_10_20_40_50_60_80_150",
        "upgradeGold": "0_120_240_600_1200_1800_2000_3000_3600_4800_9000",
        "lvLife": "270_276_282_288_294_300_306_312_318_324",
        "lvAtk": "80_99_118_137_156_175_194_213_232_251"
    },
    {
        "id": 92,
        "name": "美狄丝",
        "raceName": "地狱",
        "race": 4,
        "quality": 1,
        "attackID": 248,
        "cardFrame": 6,
        "img": "https://cdnzmg.zmfamily.cn/card/res/herov3/mds_6_92.png",
        "attack": 105,
        "life": 310,
        "skill1": null,
        "skill2": 74,
        "skill3": 163,
        "atkPro": 18,
        "lifePro": 8,
        "upgradeNum": "0_2_4_10_20_40_50_60_80_150",
        "upgradeGold": "0_120_240_600_1200_1800_2000_3000_3600_4800_9000",
        "lvLife": "310_318_326_334_342_350_358_366_374_382",
        "lvAtk": "105_123_141_159_177_195_213_231_249_267"
    },
    {
        "id": 93,
        "name": "莉莉",
        "raceName": "地狱",
        "race": 4,
        "quality": 1,
        "attackID": 244,
        "cardFrame": 1,
        "img": "https://cdnzmg.zmfamily.cn/card/res/herov3/ll_1_93.png",
        "attack": 85,
        "life": 270,
        "skill1": 126,
        "skill2": 162,
        "skill3": 82,
        "atkPro": 19,
        "lifePro": 6,
        "upgradeNum": "0_2_4_10_20_40_50_60_80_150",
        "upgradeGold": "0_120_240_600_1200_1800_2000_3000_3600_4800_9000",
        "lvLife": "270_276_282_288_294_300_306_312_318_324",
        "lvAtk": "85_104_123_142_161_180_199_218_237_256"
    },
    {
        "id": 94,
        "name": "赵",
        "raceName": "地狱",
        "race": 4,
        "quality": 1,
        "attackID": 244,
        "cardFrame": 1,
        "img": "https://cdnzmg.zmfamily.cn/card/res/herov3/zao_1_94.png",
        "attack": 100,
        "life": 400,
        "skill1": null,
        "skill2": 170,
        "skill3": 127,
        "atkPro": 15,
        "lifePro": 20,
        "upgradeNum": "0_2_4_10_20_40_50_60_80_150",
        "upgradeGold": "0_120_240_600_1200_1800_2000_3000_3600_4800_9000",
        "lvLife": "400_420_440_460_480_500_520_540_560_580",
        "lvAtk": "100_115_130_145_160_175_190_205_220_235"
    },
    {
        "id": 95,
        "name": "尼莫西妮",
        "raceName": "地狱",
        "race": 4,
        "quality": 1,
        "attackID": 248,
        "cardFrame": 6,
        "img": "https://cdnzmg.zmfamily.cn/card/res/herov3/nmxn_6_95.png",
        "attack": 90,
        "life": 290,
        "skill1": null,
        "skill2": 166,
        "skill3": 7,
        "atkPro": 20,
        "lifePro": 7,
        "upgradeNum": "0_2_4_10_20_40_50_60_80_150",
        "upgradeGold": "0_120_240_600_1200_1800_2000_3000_3600_4800_9000",
        "lvLife": "290_297_304_311_318_325_332_339_346_353",
        "lvAtk": "90_110_130_150_170_190_210_230_250_270"
    },
    {
        "id": 96,
        "name": "珀耳修斯",
        "raceName": "地狱",
        "race": 4,
        "quality": 2,
        "attackID": 244,
        "cardFrame": 2,
        "img": "https://cdnzmg.zmfamily.cn/card/res/herov3/pexs_2_96.png",
        "attack": 105,
        "life": 470,
        "skill1": 49,
        "skill2": 38,
        "skill3": 73,
        "atkPro": 23,
        "lifePro": 11,
        "upgradeNum": "0_2_4_6_10_20_30_40_60_80_120",
        "upgradeGold": "0_330_660_990_1650_3300_4950_6600_9900_13200_19800",
        "lvLife": "470_481_492_503_514_525_536_547_558_569",
        "lvAtk": "105_128_151_174_197_220_243_266_289_312"
    },
    {
        "id": 97,
        "name": "狄刻",
        "raceName": "地狱",
        "race": 4,
        "quality": 2,
        "attackID": 248,
        "cardFrame": 6,
        "img": "https://cdnzmg.zmfamily.cn/card/res/herov3/dk_6_97.png",
        "attack": 125,
        "life": 390,
        "skill1": 101,
        "skill2": 127,
        "skill3": 162,
        "atkPro": 19,
        "lifePro": 21,
        "upgradeNum": "0_2_4_6_10_20_30_40_60_80_120",
        "upgradeGold": "0_330_660_990_1650_3300_4950_6600_9900_13200_19800",
        "lvLife": "390_411_432_453_474_495_516_537_558_579",
        "lvAtk": "125_144_163_182_201_220_239_258_277_296"
    },
    {
        "id": 98,
        "name": "代达罗斯",
        "raceName": "地狱",
        "race": 4,
        "quality": 2,
        "attackID": 244,
        "cardFrame": 1,
        "img": "https://cdnzmg.zmfamily.cn/card/res/herov3/fdls_1_98.png",
        "attack": 105,
        "life": 400,
        "skill1": 25,
        "skill2": 72,
        "skill3": 127,
        "atkPro": 22,
        "lifePro": 15,
        "upgradeNum": "0_2_4_6_10_20_30_40_60_80_120",
        "upgradeGold": "0_330_660_990_1650_3300_4950_6600_9900_13200_19800",
        "lvLife": "400_415_430_445_460_475_490_505_520_535",
        "lvAtk": "105_127_149_171_193_215_237_259_281_303"
    },
    {
        "id": 99,
        "name": "帕拉斯",
        "raceName": "地狱",
        "race": 4,
        "quality": 2,
        "attackID": 244,
        "cardFrame": 1,
        "img": "https://cdnzmg.zmfamily.cn/card/res/herov3/pls_1_99.png",
        "attack": 155,
        "life": 530,
        "skill1": null,
        "skill2": 72,
        "skill3": 123,
        "atkPro": 24,
        "lifePro": 7,
        "upgradeNum": "0_2_4_6_10_20_30_40_60_80_120",
        "upgradeGold": "0_330_660_990_1650_3300_4950_6600_9900_13200_19800",
        "lvLife": "530_537_544_551_558_565_572_579_586_593",
        "lvAtk": "155_179_203_227_251_275_299_323_347_371"
    },
    {
        "id": 100,
        "name": "拉达曼达斯",
        "raceName": "地狱",
        "race": 4,
        "quality": 2,
        "attackID": 248,
        "cardFrame": 6,
        "img": "https://cdnzmg.zmfamily.cn/card/res/herov3/ldmds_6_100.png",
        "attack": 135,
        "life": 480,
        "skill1": 3,
        "skill2": 63,
        "skill3": 107,
        "atkPro": 22,
        "lifePro": 16,
        "upgradeNum": "0_2_4_6_10_20_30_40_60_80_120",
        "upgradeGold": "0_330_660_990_1650_3300_4950_6600_9900_13200_19800",
        "lvLife": "480_496_512_528_544_560_576_592_608_624",
        "lvAtk": "135_157_179_201_223_245_267_289_311_333"
    },
    {
        "id": 101,
        "name": "爱丽丝",
        "raceName": "地狱",
        "race": 4,
        "quality": 2,
        "attackID": 247,
        "cardFrame": 2,
        "img": "https://cdnzmg.zmfamily.cn/card/res/herov3/als_2_101.png",
        "attack": 160,
        "life": 500,
        "skill1": null,
        "skill2": 74,
        "skill3": 43,
        "atkPro": 15,
        "lifePro": 15,
        "upgradeNum": "0_2_4_6_10_20_30_40_60_80_120",
        "upgradeGold": "0_330_660_990_1650_3300_4950_6600_9900_13200_19800",
        "lvLife": "500_515_530_545_560_575_590_605_620_635",
        "lvAtk": "160_175_190_205_220_235_250_265_280_295"
    },
    {
        "id": 102,
        "name": "欧律诺墨",
        "raceName": "地狱",
        "race": 4,
        "quality": 2,
        "attackID": 244,
        "cardFrame": 1,
        "img": "https://cdnzmg.zmfamily.cn/card/res/herov3/olnm_1_102.png",
        "attack": 205,
        "life": 520,
        "skill1": 10,
        "skill2": 123,
        "skill3": 242,
        "atkPro": 13,
        "lifePro": 20,
        "upgradeNum": "0_2_4_6_10_20_30_40_60_80_120",
        "upgradeGold": "0_330_660_990_1650_3300_4950_6600_9900_13200_19800",
        "lvLife": "520_540_560_580_600_620_640_660_680_700",
        "lvAtk": "205_218_231_244_257_270_283_296_309_322"
    },
    {
        "id": 103,
        "name": "厄俄斯",
        "raceName": "地狱",
        "race": 4,
        "quality": 2,
        "attackID": 244,
        "cardFrame": 4,
        "img": "https://cdnzmg.zmfamily.cn/card/res/herov3/els_4_103.png",
        "attack": 100,
        "life": 370,
        "skill1": 38,
        "skill2": 174,
        "skill3": 30,
        "atkPro": 14,
        "lifePro": 36,
        "upgradeNum": "0_2_4_6_10_20_30_40_60_80_120",
        "upgradeGold": "0_330_660_990_1650_3300_4950_6600_9900_13200_19800",
        "lvLife": "370_406_442_478_514_550_586_622_658_694",
        "lvAtk": "100_114_128_142_156_170_184_198_212_226"
    },
    {
        "id": 104,
        "name": "塔那托斯",
        "raceName": "地狱",
        "race": 4,
        "quality": 3,
        "attackID": 244,
        "cardFrame": 4,
        "img": "https://cdnzmg.zmfamily.cn/card/res/herov3/tnts_4_104.png",
        "attack": 150,
        "life": 700,
        "skill1": 25,
        "skill2": 171,
        "skill3": 51,
        "atkPro": 27,
        "lifePro": 13,
        "upgradeNum": "0_2_3_4_6_10_20_30_40_50_80",
        "upgradeGold": "0_840_1260_1680_2520_4200_8400_12600_16800_21000_33600",
        "lvLife": "700_713_726_739_752_765_778_791_804_817",
        "lvAtk": "150_177_204_231_258_285_312_339_366_393"
    },
    {
        "id": 105,
        "name": "塞勒涅",
        "raceName": "地狱",
        "race": 4,
        "quality": 3,
        "attackID": 246,
        "cardFrame": 3,
        "img": "https://cdnzmg.zmfamily.cn/card/res/herov3/sln_3_105.png",
        "attack": 115,
        "life": 520,
        "skill1": 50,
        "skill2": 206,
        "skill3": 128,
        "atkPro": 24,
        "lifePro": 23,
        "upgradeNum": "0_2_3_4_6_10_20_30_40_50_80",
        "upgradeGold": "0_840_1260_1680_2520_4200_8400_12600_16800_21000_33600",
        "lvLife": "520_543_566_589_612_635_658_681_704_727",
        "lvAtk": "115_139_163_187_211_235_259_283_307_331"
    },
    {
        "id": 106,
        "name": "安德洛玛",
        "raceName": "地狱",
        "race": 4,
        "quality": 3,
        "attackID": 244,
        "cardFrame": 1,
        "img": "https://cdnzmg.zmfamily.cn/card/res/herov3/adlm_1_106.png",
        "attack": 165,
        "life": 590,
        "skill1": 237,
        "skill2": 11,
        "skill3": 242,
        "atkPro": 29,
        "lifePro": 8,
        "upgradeNum": "0_2_3_4_6_10_20_30_40_50_80",
        "upgradeGold": "0_840_1260_1680_2520_4200_8400_12600_16800_21000_33600",
        "lvLife": "590_598_606_614_622_630_638_646_654_662",
        "lvAtk": "165_194_223_252_281_310_339_368_397_426"
    },
    {
        "id": 107,
        "name": "安菲翁",
        "raceName": "地狱",
        "race": 4,
        "quality": 3,
        "attackID": 244,
        "cardFrame": 1,
        "img": "https://cdnzmg.zmfamily.cn/card/res/herov3/afw_1_107.png",
        "attack": 130,
        "life": 560,
        "skill1": 43,
        "skill2": 75,
        "skill3": 139,
        "atkPro": 21,
        "lifePro": 31,
        "upgradeNum": "0_2_3_4_6_10_20_30_40_50_80",
        "upgradeGold": "0_840_1260_1680_2520_4200_8400_12600_16800_21000_33600",
        "lvLife": "560_591_622_653_684_715_746_777_808_839",
        "lvAtk": "130_151_172_193_214_235_256_277_298_319"
    },
    {
        "id": 108,
        "name": "克洛诺斯",
        "raceName": "地狱",
        "race": 4,
        "quality": 3,
        "attackID": 244,
        "cardFrame": 5,
        "img": "https://cdnzmg.zmfamily.cn/card/res/herov3/klns_5_108.png",
        "attack": 180,
        "life": 760,
        "skill1": 9,
        "skill2": 103,
        "skill3": 124,
        "atkPro": 25,
        "lifePro": 14,
        "upgradeNum": "0_2_3_4_6_10_20_30_40_50_80",
        "upgradeGold": "0_840_1260_1680_2520_4200_8400_12600_16800_21000_33600",
        "lvLife": "760_774_788_802_816_830_844_858_872_886",
        "lvAtk": "180_205_230_255_280_305_330_355_380_405"
    },
    {
        "id": 109,
        "name": "皮拉",
        "raceName": "地狱",
        "race": 4,
        "quality": 3,
        "attackID": 248,
        "cardFrame": 6,
        "img": "https://cdnzmg.zmfamily.cn/card/res/herov3/pl_6_109.png",
        "attack": 170,
        "life": 700,
        "skill1": 10,
        "skill2": 7,
        "skill3": 107,
        "atkPro": 27,
        "lifePro": 14,
        "upgradeNum": "0_2_3_4_6_10_20_30_40_50_80",
        "upgradeGold": "0_840_1260_1680_2520_4200_8400_12600_16800_21000_33600",
        "lvLife": "700_714_728_742_756_770_784_798_812_826",
        "lvAtk": "170_197_224_251_278_305_332_359_386_413"
    },
    {
        "id": 110,
        "name": "曼托",
        "raceName": "地狱",
        "race": 4,
        "quality": 3,
        "attackID": 248,
        "cardFrame": 6,
        "img": "https://cdnzmg.zmfamily.cn/card/res/herov3/mt_6_110.png",
        "attack": 165,
        "life": 570,
        "skill1": 218,
        "skill2": 73,
        "skill3": 103,
        "atkPro": 23,
        "lifePro": 24,
        "upgradeNum": "0_2_3_4_6_10_20_30_40_50_80",
        "upgradeGold": "0_840_1260_1680_2520_4200_8400_12600_16800_21000_33600",
        "lvLife": "570_594_618_642_666_690_714_738_762_786",
        "lvAtk": "165_188_211_234_257_280_303_326_349_372"
    },
    {
        "id": 111,
        "name": "米诺斯",
        "raceName": "地狱",
        "race": 4,
        "quality": 3,
        "attackID": 244,
        "cardFrame": 1,
        "img": "https://cdnzmg.zmfamily.cn/card/res/herov3/mns_1_111.png",
        "attack": 180,
        "life": 650,
        "skill1": 225,
        "skill2": 187,
        "skill3": 12,
        "atkPro": 24,
        "lifePro": 25,
        "upgradeNum": "0_2_3_4_6_10_20_30_40_50_80",
        "upgradeGold": "0_840_1260_1680_2520_4200_8400_12600_16800_21000_33600",
        "lvLife": "650_675_700_725_750_775_800_825_850_875",
        "lvAtk": "180_204_228_252_276_300_324_348_372_396"
    },
    {
        "id": 112,
        "name": "墨诺提俄斯",
        "raceName": "地狱",
        "race": 4,
        "quality": 3,
        "attackID": 244,
        "cardFrame": 1,
        "img": "https://cdnzmg.zmfamily.cn/card/res/herov3/mntes_1_112.png",
        "attack": 200,
        "life": 785,
        "skill1": 74,
        "skill2": 176,
        "skill3": 115,
        "atkPro": 28,
        "lifePro": 11,
        "upgradeNum": "0_2_3_4_6_10_20_30_40_50_80",
        "upgradeGold": "0_840_1260_1680_2520_4200_8400_12600_16800_21000_33600",
        "lvLife": "785_796_807_818_829_840_851_862_873_884",
        "lvAtk": "200_228_256_284_312_340_368_396_424_452"
    },
    {
        "id": 113,
        "name": "赫西俄",
        "raceName": "地狱",
        "race": 4,
        "quality": 4,
        "attackID": 246,
        "cardFrame": 3,
        "img": "https://cdnzmg.zmfamily.cn/card/res/herov3/hxe_3_113.png",
        "attack": 230,
        "life": 870,
        "skill1": 76,
        "skill2": 21,
        "skill3": 231,
        "atkPro": 28,
        "lifePro": 23,
        "upgradeNum": "0_0_2_3_4_6_8_10_14_20_30",
        "upgradeGold": "0_0_3550_5325_7100_10650_14200_17750_24850_35500_53250",
        "lvLife": "870_893_916_939_962_985_1008_1031_1054_1077",
        "lvAtk": "230_258_286_314_342_370_398_426_454_482"
    },
    {
        "id": 114,
        "name": "哈迪斯",
        "raceName": "地狱",
        "race": 4,
        "quality": 4,
        "attackID": 244,
        "cardFrame": 1,
        "img": "https://cdnzmg.zmfamily.cn/card/res/herov3/hds_1_114.png",
        "attack": 195,
        "life": 700,
        "skill1": 3,
        "skill2": 76,
        "skill3": 127,
        "atkPro": 29,
        "lifePro": 22,
        "upgradeNum": "0_0_2_3_4_6_8_10_14_20_30",
        "upgradeGold": "0_0_3550_5325_7100_10650_14200_17750_24850_35500_53250",
        "lvLife": "700_722_744_766_788_810_832_854_876_898",
        "lvAtk": "195_224_253_282_311_340_369_398_427_456"
    },
    {
        "id": 115,
        "name": "厄毗米修斯",
        "raceName": "地狱",
        "race": 4,
        "quality": 4,
        "attackID": 244,
        "cardFrame": 1,
        "img": "https://cdnzmg.zmfamily.cn/card/res/herov3/ezmxs_1_115.png",
        "attack": 250,
        "life": 850,
        "skill1": 203,
        "skill2": 242,
        "skill3": 128,
        "atkPro": 26,
        "lifePro": 15,
        "upgradeNum": "0_0_2_3_4_6_8_10_14_20_30",
        "upgradeGold": "0_0_3550_5325_7100_10650_14200_17750_24850_35500_53250",
        "lvLife": "850_865_880_895_910_925_940_955_970_985",
        "lvAtk": "250_276_302_328_354_380_406_432_458_484"
    },
    {
        "id": 116,
        "name": "阿勒克图",
        "raceName": "地狱",
        "race": 4,
        "quality": 4,
        "attackID": 244,
        "cardFrame": 1,
        "img": "https://cdnzmg.zmfamily.cn/card/res/herov3/alkt_1_116.png",
        "attack": 225,
        "life": 900,
        "skill1": 75,
        "skill2": 8,
        "skill3": 119,
        "atkPro": 30,
        "lifePro": 19,
        "upgradeNum": "0_0_2_3_4_6_8_10_14_20_30",
        "upgradeGold": "0_0_3550_5325_7100_10650_14200_17750_24850_35500_53250",
        "lvLife": "900_919_938_957_976_995_1014_1033_1052_1071",
        "lvAtk": "225_255_285_315_345_375_405_435_465_495"
    },
    {
        "id": 117,
        "name": "贝瑟芬妮",
        "raceName": "地狱",
        "race": 4,
        "quality": 4,
        "attackID": 244,
        "cardFrame": 1,
        "img": "https://cdnzmg.zmfamily.cn/card/res/herov3/bsfn_1_117.png",
        "attack": 240,
        "life": 850,
        "skill1": 46,
        "skill2": 75,
        "skill3": 111,
        "atkPro": 35,
        "lifePro": 40,
        "upgradeNum": "0_0_2_3_4_6_8_10_14_20_30",
        "upgradeGold": "0_0_3550_5325_7100_10650_14200_17750_24850_35500_53250",
        "lvLife": "850_890_930_970_1010_1050_1090_1130_1170_1210",
        "lvAtk": "240_275_310_345_380_415_450_485_520_555"
    },
    {
        "id": 118,
        "name": "赫卡忒",
        "raceName": "地狱",
        "race": 4,
        "quality": 4,
        "attackID": 244,
        "cardFrame": 1,
        "img": "https://cdnzmg.zmfamily.cn/card/res/herov3/hkr_1_118.png",
        "attack": 295,
        "life": 1250,
        "skill1": 191,
        "skill2": 124,
        "skill3": 12,
        "atkPro": 25,
        "lifePro": 26,
        "upgradeNum": "0_0_2_3_4_6_8_10_14_20_30",
        "upgradeGold": "0_0_3550_5325_7100_10650_14200_17750_24850_35500_53250",
        "lvLife": "1250_1276_1302_1328_1354_1380_1406_1432_1458_1484",
        "lvAtk": "295_320_345_370_395_420_445_470_495_520"
    },
    {
        "id": 119,
        "name": "墨纪拉",
        "raceName": "地狱",
        "race": 4,
        "quality": 5,
        "attackID": 244,
        "cardFrame": 1,
        "img": "https://cdnzmg.zmfamily.cn/card/res/herov3/mjl_1_119.png",
        "attack": 350,
        "life": 1350,
        "skill1": 243,
        "skill2": 198,
        "skill3": 204,
        "atkPro": 34,
        "lifePro": 24,
        "upgradeNum": "0_0_0_2_3_4_6_8_10_12_20",
        "upgradeGold": "0_0_0_6600_9900_13200_19800_26400_33000_39600_66000",
        "lvLife": "1350_1374_1398_1422_1446_1470_1494_1518_1542_1566",
        "lvAtk": "350_384_418_452_486_520_554_588_622_656"
    },
    {
        "id": 120,
        "name": "赫拉",
        "raceName": "地狱",
        "race": 4,
        "quality": 5,
        "attackID": 248,
        "cardFrame": 6,
        "img": "https://cdnzmg.zmfamily.cn/card/res/herov3/hl_6_120.png",
        "attack": 365,
        "life": 1300,
        "skill1": 105,
        "skill2": 48,
        "skill3": 4,
        "atkPro": 26,
        "lifePro": 40,
        "upgradeNum": "0_0_0_2_3_4_6_8_10_12_20",
        "upgradeGold": "0_0_0_6600_9900_13200_19800_26400_33000_39600_66000",
        "lvLife": "1300_1340_1380_1420_1460_1500_1540_1580_1620_1660",
        "lvAtk": "365_391_417_443_469_495_521_547_573_599"
    },
    {
        "id": 121,
        "name": "厄里斯",
        "raceName": "王国",
        "race": 2,
        "quality": 4,
        "attackID": 244,
        "cardFrame": 4,
        "img": "https://cdnzmg.zmfamily.cn/card/res/herov3/els_4_121.png",
        "attack": 220,
        "life": 820,
        "skill1": 234,
        "skill2": 231,
        "skill3": 143,
        "atkPro": 12,
        "lifePro": 50,
        "upgradeNum": "0_0_2_3_4_6_8_10_14_20_30",
        "upgradeGold": "0_0_3550_5325_7100_10650_14200_17750_24850_35500_53250",
        "lvLife": "820_870_920_970_1020_1070_1120_1170_1220_1270",
        "lvAtk": "220_232_244_256_268_280_292_304_316_328"
    },
    {
        "id": 122,
        "name": "海伦",
        "raceName": "王国",
        "race": 2,
        "quality": 3,
        "attackID": 246,
        "cardFrame": 3,
        "img": "https://cdnzmg.zmfamily.cn/card/res/herov3/hl_3_122.png",
        "attack": 170,
        "life": 600,
        "skill1": 135,
        "skill2": 10,
        "skill3": 91,
        "atkPro": 20,
        "lifePro": 30,
        "upgradeNum": "0_2_3_4_6_10_20_30_40_50_80",
        "upgradeGold": "0_840_1260_1680_2520_4200_8400_12600_16800_21000_33600",
        "lvLife": "600_630_660_690_720_750_780_810_840_870",
        "lvAtk": "170_190_210_230_250_270_290_310_330_350"
    },
    {
        "id": 123,
        "name": "娜娜",
        "raceName": "森林",
        "race": 1,
        "quality": 4,
        "attackID": 244,
        "cardFrame": 5,
        "img": "https://cdnzmg.zmfamily.cn/card/res/herov3/nn_5_123.png",
        "attack": 230,
        "life": 700,
        "skill1": 98,
        "skill2": 239,
        "skill3": 204,
        "atkPro": 15,
        "lifePro": 25,
        "upgradeNum": "0_0_2_3_4_6_8_10_14_20_30",
        "upgradeGold": "0_0_3550_5325_7100_10650_14200_17750_24850_35500_53250",
        "lvLife": "700_725_750_775_800_825_850_875_900_925",
        "lvAtk": "230_245_260_275_290_305_320_335_350_365"
    },
    {
        "id": 124,
        "name": "俄里翁",
        "raceName": "森林",
        "race": 1,
        "quality": 2,
        "attackID": 244,
        "cardFrame": 7,
        "img": "https://cdnzmg.zmfamily.cn/card/res/herov3/elw_7_124.png",
        "attack": 130,
        "life": 450,
        "skill1": 81,
        "skill2": 225,
        "skill3": 167,
        "atkPro": 14,
        "lifePro": 32,
        "upgradeNum": "0_2_4_6_10_20_30_40_60_80_120",
        "upgradeGold": "0_330_660_990_1650_3300_4950_6600_9900_13200_19800",
        "lvLife": "450_482_514_546_578_610_642_674_706_738",
        "lvAtk": "130_144_158_172_186_200_214_228_242_256"
    },
    {
        "id": 125,
        "name": "许德拉",
        "raceName": "蛮荒",
        "race": 3,
        "quality": 3,
        "attackID": 248,
        "cardFrame": 6,
        "img": "https://cdnzmg.zmfamily.cn/card/res/herov3/xdl_6_125.png",
        "attack": 200,
        "life": 700,
        "skill1": 82,
        "skill2": 103,
        "skill3": 164,
        "atkPro": 20,
        "lifePro": 20,
        "upgradeNum": "0_2_3_4_6_10_20_30_40_50_80",
        "upgradeGold": "0_840_1260_1680_2520_4200_8400_12600_16800_21000_33600",
        "lvLife": "700_720_740_760_780_800_820_840_860_880",
        "lvAtk": "200_220_240_260_280_300_320_340_360_380"
    },
    {
        "id": 126,
        "name": "提希丰",
        "raceName": "地狱",
        "race": 4,
        "quality": 3,
        "attackID": 244,
        "cardFrame": 1,
        "img": "https://cdnzmg.zmfamily.cn/card/res/herov3/txf_1_126.png",
        "attack": 180,
        "life": 700,
        "skill1": 85,
        "skill2": 75,
        "skill3": 17,
        "atkPro": 23,
        "lifePro": 26,
        "upgradeNum": "0_2_3_4_6_10_20_30_40_50_80",
        "upgradeGold": "0_840_1260_1680_2520_4200_8400_12600_16800_21000_33600",
        "lvLife": "700_726_752_778_804_830_856_882_908_934",
        "lvAtk": "180_203_226_249_272_295_318_341_364_387"
    },
    {
        "id": 127,
        "name": "布里塞伊丝",
        "raceName": "地狱",
        "race": 3,
        "quality": 4,
        "attackID": 248,
        "cardFrame": 6,
        "img": "https://cdnzmg.zmfamily.cn/card/res/herov3/blsys_6_127.png",
        "attack": 260,
        "life": 960,
        "skill1": 164,
        "skill2": 87,
        "skill3": 12,
        "atkPro": 10,
        "lifePro": 40,
        "upgradeNum": "0_0_2_3_4_6_8_10_14_20_30",
        "upgradeGold": "0_0_3550_5325_7100_10650_14200_17750_24850_35500_53250",
        "lvLife": "960_1000_1040_1080_1120_1160_1200_1240_1280_1320",
        "lvAtk": "260_270_280_290_300_310_320_330_340_350"
    },
    {
        "id": 128,
        "name": "伊俄",
        "raceName": "地狱",
        "race": 4,
        "quality": 4,
        "attackID": 244,
        "cardFrame": 6,
        "img": "https://cdnzmg.zmfamily.cn/card/res/herov3/ye_6_128.png",
        "attack": 225,
        "life": 750,
        "skill1": 188,
        "skill2": 143,
        "skill3": 198,
        "atkPro": 30,
        "lifePro": 38,
        "upgradeNum": "0_0_2_3_4_6_8_10_14_20_30",
        "upgradeGold": "0_0_3550_5325_7100_10650_14200_17750_24850_35500_53250",
        "lvLife": "750_788_826_864_902_940_978_1016_1054_1092",
        "lvAtk": "225_255_285_315_345_375_405_435_465_495"
    },
    {
        "id": 129,
        "name": "该亚",
        "raceName": "蛮荒",
        "race": 3,
        "quality": 2,
        "attackID": 244,
        "cardFrame": 1,
        "img": "https://cdnzmg.zmfamily.cn/card/res/herov3/gy_1_129.png",
        "attack": 100,
        "life": 470,
        "skill1": 70,
        "skill2": 10,
        "skill3": 103,
        "atkPro": 20,
        "lifePro": 20,
        "upgradeNum": "0_2_4_6_10_20_30_40_60_80_120",
        "upgradeGold": "0_330_660_990_1650_3300_4950_6600_9900_13200_19800",
        "lvLife": "470_490_510_530_550_570_590_610_630_650",
        "lvAtk": "100_120_140_160_180_200_220_240_260_280"
    },
    {
        "id": 130,
        "name": "卡珊德拉",
        "raceName": "地狱",
        "race": 4,
        "quality": 2,
        "attackID": 248,
        "cardFrame": 6,
        "img": "https://cdnzmg.zmfamily.cn/card/res/herov3/ksdl_6_130.png",
        "attack": 120,
        "life": 400,
        "skill1": 70,
        "skill2": 10,
        "skill3": 126,
        "atkPro": 23,
        "lifePro": 18,
        "upgradeNum": "0_2_4_6_10_20_30_40_60_80_120",
        "upgradeGold": "0_330_660_990_1650_3300_4950_6600_9900_13200_19800",
        "lvLife": "400_418_436_454_472_490_508_526_544_562",
        "lvAtk": "120_143_166_189_212_235_258_281_304_327"
    },
    {
        "id": 131,
        "name": "忒弥斯",
        "raceName": "森林",
        "race": 1,
        "quality": 3,
        "attackID": 244,
        "cardFrame": 2,
        "img": "https://cdnzmg.zmfamily.cn/card/res/herov3/rms_2_131.png",
        "attack": 150,
        "life": 600,
        "skill1": 39,
        "skill2": 83,
        "skill3": 195,
        "atkPro": 20,
        "lifePro": 20,
        "upgradeNum": "0_2_3_4_6_10_20_30_40_50_80",
        "upgradeGold": "0_840_1260_1680_2520_4200_8400_12600_16800_21000_33600",
        "lvLife": "600_620_640_660_680_700_720_740_760_780",
        "lvAtk": "150_170_190_210_230_250_270_290_310_330"
    },
    {
        "id": 132,
        "name": "卡德摩斯",
        "raceName": "王国",
        "race": 2,
        "quality": 3,
        "attackID": 244,
        "cardFrame": 3,
        "img": "https://cdnzmg.zmfamily.cn/card/res/herov3/kdxm_3_132.png",
        "attack": 190,
        "life": 650,
        "skill1": 241,
        "skill2": 11,
        "skill3": 198,
        "atkPro": 26,
        "lifePro": 30,
        "upgradeNum": "0_2_3_4_6_10_20_30_40_50_80",
        "upgradeGold": "0_840_1260_1680_2520_4200_8400_12600_16800_21000_33600",
        "lvLife": "650_680_710_740_770_800_830_860_890_920",
        "lvAtk": "190_216_242_268_294_320_346_372_398_424"
    },
    {
        "id": 133,
        "name": "瑞亚",
        "raceName": "森林",
        "race": 1,
        "quality": 4,
        "attackID": 244,
        "cardFrame": 5,
        "img": "https://cdnzmg.zmfamily.cn/card/res/herov3/ry_5_133.png",
        "attack": 225,
        "life": 790,
        "skill1": 98,
        "skill2": 118,
        "skill3": 22,
        "atkPro": 25,
        "lifePro": 25,
        "upgradeNum": "0_0_2_3_4_6_8_10_14_20_30",
        "upgradeGold": "0_0_3550_5325_7100_10650_14200_17750_24850_35500_53250",
        "lvLife": "790_815_840_865_890_915_940_965_990_1015",
        "lvAtk": "225_250_275_300_325_350_375_400_425_450"
    },
    {
        "id": 134,
        "name": "赫淮斯托",
        "raceName": "王国",
        "race": 2,
        "quality": 4,
        "attackID": 246,
        "cardFrame": 3,
        "img": "https://cdnzmg.zmfamily.cn/card/res/herov3/hhst_3_134.png",
        "attack": 240,
        "life": 840,
        "skill1": 201,
        "skill2": 111,
        "skill3": 56,
        "atkPro": 22,
        "lifePro": 20,
        "upgradeNum": "0_0_2_3_4_6_8_10_14_20_30",
        "upgradeGold": "0_0_3550_5325_7100_10650_14200_17750_24850_35500_53250",
        "lvLife": "840_860_880_900_920_940_960_980_1000_1020",
        "lvAtk": "240_262_284_306_328_350_372_394_416_438"
    },
    {
        "id": 135,
        "name": "西亚",
        "raceName": "蛮荒",
        "race": 3,
        "quality": 4,
        "attackID": 244,
        "cardFrame": 1,
        "img": "https://cdnzmg.zmfamily.cn/card/res/herov3/xy_1_135.png",
        "attack": 260,
        "life": 800,
        "skill1": 201,
        "skill2": 125,
        "skill3": 168,
        "atkPro": 19,
        "lifePro": 25,
        "upgradeNum": "0_0_2_3_4_6_8_10_14_20_30",
        "upgradeGold": "0_0_3550_5325_7100_10650_14200_17750_24850_35500_53250",
        "lvLife": "800_825_850_875_900_925_950_975_1000_1025",
        "lvAtk": "260_279_298_317_336_355_374_393_412_431"
    },
    {
        "id": 136,
        "name": "奇美拉",
        "raceName": "地狱",
        "race": 4,
        "quality": 4,
        "attackID": 245,
        "cardFrame": 4,
        "img": "https://cdnzmg.zmfamily.cn/card/res/herov3/qml_4_136.png",
        "attack": 160,
        "life": 700,
        "skill1": 52,
        "skill2": 111,
        "skill3": 214,
        "atkPro": 44,
        "lifePro": 18,
        "upgradeNum": "0_0_2_3_4_6_8_10_14_20_30",
        "upgradeGold": "0_0_3550_5325_7100_10650_14200_17750_24850_35500_53250",
        "lvLife": "700_718_736_754_772_790_808_826_844_862",
        "lvAtk": "160_204_248_292_336_380_424_468_512_556"
    },
    {
        "id": 137,
        "name": "克瑞斯",
        "raceName": "森林",
        "race": 1,
        "quality": 5,
        "attackID": 245,
        "cardFrame": 4,
        "img": "https://cdnzmg.zmfamily.cn/card/res/herov3/krs_4_137.png",
        "attack": 400,
        "life": 1350,
        "skill1": 202,
        "skill2": 92,
        "skill3": 232,
        "atkPro": 30,
        "lifePro": 45,
        "upgradeNum": "0_0_0_2_3_4_6_8_10_12_20",
        "upgradeGold": "0_0_0_6600_9900_13200_19800_26400_33000_39600_66000",
        "lvLife": "1350_1395_1440_1485_1530_1575_1620_1665_1710_1755",
        "lvAtk": "400_430_460_490_520_550_580_610_640_670"
    },
    {
        "id": 138,
        "name": "喀耳刻",
        "raceName": "王国",
        "race": 2,
        "quality": 5,
        "attackID": 248,
        "cardFrame": 6,
        "img": "https://cdnzmg.zmfamily.cn/card/res/herov3/kek_6_138.png",
        "attack": 350,
        "life": 1200,
        "skill1": 145,
        "skill2": 239,
        "skill3": 165,
        "atkPro": 40,
        "lifePro": 30,
        "upgradeNum": "0_0_0_2_3_4_6_8_10_12_20",
        "upgradeGold": "0_0_0_6600_9900_13200_19800_26400_33000_39600_66000",
        "lvLife": "1200_1230_1260_1290_1320_1350_1380_1410_1440_1470",
        "lvAtk": "350_390_430_470_510_550_590_630_670_710"
    },
    {
        "id": 139,
        "name": "阿塔兰忒",
        "raceName": "蛮荒",
        "race": 3,
        "quality": 5,
        "attackID": 248,
        "cardFrame": 6,
        "img": "https://cdnzmg.zmfamily.cn/card/res/herov3/atlr_6_139.png",
        "attack": 360,
        "life": 1350,
        "skill1": 177,
        "skill2": 76,
        "skill3": 204,
        "atkPro": 28,
        "lifePro": 15,
        "upgradeNum": "0_0_0_2_3_4_6_8_10_12_20",
        "upgradeGold": "0_0_0_6600_9900_13200_19800_26400_33000_39600_66000",
        "lvLife": "1350_1365_1380_1395_1410_1425_1440_1455_1470_1485",
        "lvAtk": "360_388_416_444_472_500_528_556_584_612"
    },
    {
        "id": 140,
        "name": "欧申纳斯",
        "raceName": "地狱",
        "race": 4,
        "quality": 5,
        "attackID": 244,
        "cardFrame": 2,
        "img": "https://cdnzmg.zmfamily.cn/card/res/herov3/osns_2_140.png",
        "attack": 310,
        "life": 1200,
        "skill1": 72,
        "skill2": 48,
        "skill3": 129,
        "atkPro": 25,
        "lifePro": 25,
        "upgradeNum": "0_0_0_2_3_4_6_8_10_12_20",
        "upgradeGold": "0_0_0_6600_9900_13200_19800_26400_33000_39600_66000",
        "lvLife": "1200_1225_1250_1275_1300_1325_1350_1375_1400_1425",
        "lvAtk": "310_335_360_385_410_435_460_485_510_535"
    }
]