{"file":"10434.png","mc":{"10434":{"frames":[{"y":-61,"duration":1,"res":"Sprite_0","x":-55},{"y":-61,"duration":1,"res":"Sprite_1","x":-55},{"y":-61,"duration":1,"res":"Sprite_2","x":-55},{"y":-61,"duration":1,"res":"Sprite_3","x":-55},{"y":-61,"duration":1,"res":"Sprite_4","x":-55},{"y":-61,"duration":1,"res":"Sprite_5","x":-55},{"y":-61,"duration":1,"res":"Sprite_6","x":-55},{"y":-70,"duration":1,"res":"Sprite_7","x":-67},{"y":-76,"duration":1,"res":"Sprite_8","x":-70},{"y":-82,"duration":1,"res":"Sprite_9","x":-70},{"y":-88,"duration":1,"res":"Sprite_10","x":-70},{"y":-89,"duration":1,"res":"Sprite_11","x":-70},{"y":-100,"duration":1,"res":"Sprite_12","x":-70},{"y":-87,"duration":1,"res":"Sprite_13","x":-70},{"y":-86,"duration":1,"res":"Sprite_14","x":-70},{"y":-84,"duration":1,"res":"Sprite_15","x":-70},{"y":-67,"duration":1,"res":"Sprite_16","x":-70},{"y":-67,"duration":1,"res":"Sprite_17","x":-70},{"y":-67,"duration":1,"res":"Sprite_18","x":-70}],"labels":[{"end":19,"frame":1,"name":"Sprite"}],"frameRate":24,"events":[]}},"res":{"Sprite_9":{"x":853,"y":1,"w":140,"h":162},"Sprite_7":{"x":285,"y":178,"w":137,"h":136},"Sprite_11":{"x":143,"y":1,"w":140,"h":178},"Sprite_5":{"x":1,"y":189,"w":119,"h":118},"Sprite_16":{"x":569,"y":175,"w":140,"h":137},"Sprite_4":{"x":711,"y":309,"w":119,"h":118},"Sprite_13":{"x":427,"y":1,"w":140,"h":174},"Sprite_18":{"x":427,"y":177,"w":140,"h":137},"Sprite_3":{"x":243,"y":316,"w":119,"h":118},"Sprite_17":{"x":711,"y":170,"w":140,"h":137},"Sprite_8":{"x":853,"y":165,"w":140,"h":149},"Sprite_10":{"x":285,"y":1,"w":140,"h":175},"Sprite_6":{"x":143,"y":181,"w":119,"h":118},"Sprite_15":{"x":711,"y":1,"w":140,"h":167},"Sprite_2":{"x":122,"y":301,"w":119,"h":118},"Sprite_1":{"x":1,"y":309,"w":119,"h":118},"Sprite_14":{"x":569,"y":1,"w":140,"h":172},"Sprite_0":{"x":569,"y":314,"w":119,"h":118},"Sprite_12":{"x":1,"y":1,"w":140,"h":186}}}